Workbook

Sheet Sheet1
A1: =_xll.TR("SCREEN(U(IN(Equity(active,public,primary))/*UNV:Public*/), IN(TR.ExchangeMarketIdCode,""HSTC"",""XSTC""), CURN=USD)","TR.CommonName;TR.ExchangeName;TR.GICSIndustry;TR.GICSSector;TR.CompanyPublicSinceDate","curn=USD RH=In CH=Fd") -> Updated at 14:09:47 | B1: Company Common Name | C1: Exchange Name | D1: GICS Industry Name | E1: GICS Sector Name | F1: Date Became Public
A2: CHP.HM | B2: Central Hydropower JSC | C2: Ho Chi Minh Securities Trading Centre | D2: Independent Power and Renewable Electricity Producers | E2: Utilities | F2: 40288
A3: V21.HN | B3: Vinaconex 21 JSC | C3: Hanoi Stock Exchange | D3: Construction & Engineering | E3: Industrials | F3: 40289
A4: LIG.HN | B4: Licogi 13 JSC | C4: Hanoi Stock Exchange | D4: Construction & Engineering | E4: Industrials | F4: 40290
A5: MCC.HN | B5: High Grade Brick Tile Corp | C5: Hanoi Stock Exchange | D5: Construction Materials | E5: Materials | F5: 40294
A6: TET.HN | B6: Northern Textiles And Garments JSC | C6: Hanoi Stock Exchange | D6: Textiles, Apparel & Luxury Goods | E6: Consumer Discretionary | F6: 40296
A7: KSD.HN | B7: DNA Investment Joint Stock Corp | C7: Hanoi Stock Exchange | D7: Construction Materials | E7: Materials | F7: 40296
A8: NBW.HN | B8: Nha Be Water Supply JSC | C8: Hanoi Stock Exchange | D8: Water Utilities | E8: Utilities | F8: 43053
A9: TDC.HM | B9: Binh Duong Trade and Development JSC | C9: Ho Chi Minh Securities Trading Centre | D9: Real Estate Management & Development | E9: Real Estate | F9: 40302
A10: OGC.HM | B10: Ocean Group JSC | C10: Ho Chi Minh Securities Trading Centre | D10: Financial Services | E10: Financials | F10: 40302
A11: HTC.HN | B11: HocMon Trade JSC | C11: Hanoi Stock Exchange | D11: Oil, Gas & Consumable Fuels | E11: Energy | F11: 40305
A12: NVT.HM | B12: Ninh Van Bay Travel Real Estate JSC | C12: Ho Chi Minh Securities Trading Centre | D12: Real Estate Management & Development | E12: Real Estate | F12: 40305
A13: VCM.HN | B13: BV Life JSC | C13: Hanoi Stock Exchange | D13: Professional Services | E13: Industrials | F13: 40309
... A696: TCX.HM | B696: Techcom Securities JSC | C696: Ho Chi Minh Securities Trading Centre | D696: Capital Markets | E696: Financials | F696: 45951

Sheet Sheet2
A1: 43831
A2: 45966

Sheet YjRmYjVhNDgtMzdkMC00ZT
D3: AuditId=69734_107403491_STD_C66815C1-4A2B-4993-9493-C1F5453D23CA
D4: AuditId=82349_107403491_STD_9B7E228C-30CC-47A9-BF23-D89134DA4202
D5: AuditId=92481_107403491_STD_C1A1EB2F-8C68-4AFC-B7DB-C388BB41A9D4
D6: AuditId=59561940_107403491_STD_B94F5566-D734-4E4D-B3F0-2114155A5E1C
D7: AuditId=172268023_107403491_STD_B5470D9B-4C75-47BD-A598-1D30707F6D8A
D8: AuditId=192614852_107403491_STD_E565C324-8850-4FD0-B46D-2B9F69081D57
D9: AuditId=84516_107393580_STD_76DC990E-8B41-474E-80E2-19FA65173E0D
D10: AuditId=96235_107393580_STD_4584CB4A-AD7A-40A7-936A-AF5C3F599EBE
D11: AuditId=109071_107393580_STD_6C5750DE-DE26-45FE-B414-E983390575C6
D12: AuditId=118669_107393580_STD_8188729F-1D90-4755-A9D9-80055338A825
D13: AuditId=128315_107393580_STD_CBF8EFB9-56F4-444B-B436-B0CD02DCA05A
D14: AuditId=137904_107393580_STD_6B491C50-4574-46A5-AAB6-631899E467AB
... D4137: AuditId=1711_117098222_STD_B19BFE22-CAD3-466D-A384-948696FCA09A

Sheet Sheet3
A1: =_xll.RDP.Data(Sheet1!$A$2:$A$696,"TR.F.TotAssets","Period=FY0 Frq=FY SDate=#1 EDate=#2 CH=Fd RH=IN;periodenddate",B2,Sheet2!$A$1,Sheet2!$A$2) -> Updated at 14:22:46
D2: Total Assets
B3: CHP.HM | C3: 43830 | D3: 3611672910985
B4: CHP.HM | C4: 44196 | D4: 3532764723607
B5: CHP.HM | C5: 44561 | D5: 3272703458543
B6: CHP.HM | C6: 44926 | D6: 3259700449355
B7: CHP.HM | C7: 45291 | D7: 2967231114351
B8: CHP.HM | C8: 45657 | D8: 2696249961096
B9: V21.HN | C9: 43830 | D9: 414806519320
B10: V21.HN | C10: 44196 | D10: 437640548364
B11: V21.HN | C11: 44561 | D11: 335579886720
B12: V21.HN | C12: 44926 | D12: 317114172544
B13: V21.HN | C13: 45291 | D13: 323444750092
B14: V21.HN | C14: 45657 | D14: 365893379065
... B592: JVC.HM | C592: 44286 | D592: 627726330828
B593: JVC.HM | C593: 44926 | D593: NULL
B594: JVC.HM | C594: 44926 | D594: NULL
B595: JVC.HM | C595: 45291 | D595: 686676856095
B596: JVC.HM | C596: 45657 | D596: 828102672175
B597: PTB.HM | C597: 43830 | D597: 4328694369097
B598: PTB.HM | C598: 44196 | D598: 4773757358132
B599: PTB.HM | C599: 44561 | D599: 5430878287077
B600: PTB.HM | C600: 44926 | D600: 5238297875783
B601: PTB.HM | C601: 45291 | D601: 5263776311415
B602: PTB.HM | C602: 45657 | D602: 5489132951980
B603: CIG.HM | C603: 43830 | D603: 897151888608
B604: CIG.HM | C604: 44196 | D604: 687011930094
B605: CIG.HM | C605: 44561 | D605: 707502590681
B606: CIG.HM | C606: 44926 | D606: 729551648070
... B1685: ICT.HM | C1685: 45657 | D1685: 1475380141521
B1686: NO1.HM | D1686: Unable to collect data for the field 'TR.F.TotAssets' and some specific identifier(s).
B1687: PCH.HN | C1687: 43830 | D1687: 175641839663
B1688: PCH.HN | C1688: 44196 | D1688: 213749477804
B1689: PCH.HN | C1689: 44561 | D1689: 233655716736
B1690: PCH.HN | C1690: 44926 | D1690: 257234571546
B1691: PCH.HN | C1691: 45291 | D1691: 270339071591
B1692: PCH.HN | C1692: 45657 | D1692: 283620919180
B1693: DVM.HN | C1693: 44196 | D1693: 820855245958
B1694: DVM.HN | C1694: 44561 | D1694: 1032942899927
B1695: DVM.HN | C1695: 44926 | D1695: 1359265929276
B1696: DVM.HN | C1696: 45291 | D1696: 1532920518617
B1697: DVM.HN | C1697: 45657 | D1697: 1634570045617
B1698: CAR.HN | C1698: 45291 | D1698: 49557846457
... B1763: DXS.HM | C1763: 45657 | D1763: 15068518802220
B1764: CST.HN | C1764: 44196 | D1764: NULL
B1765: CST.HN | C1765: 44561 | D1765: 3076551236046
B1766: CST.HN | C1766: 44926 | D1766: 2369732633140
B1767: CST.HN | C1767: 45291 | D1767: 2409827943476
B1768: CST.HN | C1768: 45657 | D1768: 2651371483986
B1769: SCG.HN | C1769: 43830 | D1769: 401884876944
B1770: SCG.HN | C1770: 44196 | D1770: 1344047668192
B1771: SCG.HN | C1771: 44561 | D1771: 4871164108824
B1772: SCG.HN | C1772: 44926 | D1772: 7505300596561
B1773: SCG.HN | C1773: 45291 | D1773: 6799012338212
B1774: SCG.HN | C1774: 45657 | D1774: 8501549904096
B1775: AAT.HM | C1775: 43830 | D1775: 600879702213
B1776: AAT.HM | C1776: 44196 | D1776: 579863831008
... B2890: DPM.HM | C2890: 45657 | D2890: 16552286447507
B2891: VPL.HM | C2891: 43830 | D2891: NULL
B2892: VPL.HM | C2892: 44196 | D2892: NULL
B2893: VPL.HM | C2893: 44561 | D2893: NULL
B2894: VPL.HM | C2894: 44926 | D2894: NULL
B2895: VPL.HM | C2895: 45291 | D2895: 44072730000000
B2896: DQC.HM | C2896: 43830 | D2896: 1502043843336
B2897: DQC.HM | C2897: 44196 | D2897: 1409648867654
B2898: DQC.HM | C2898: 44561 | D2898: 1410152876407
B2899: DQC.HM | C2899: 44926 | D2899: 1485087786958
B2900: DQC.HM | C2900: 45291 | D2900: 1444059322753
B2901: DQC.HM | C2901: 45657 | D2901: 1209917381905
B2902: PIT.HM | C2902: 43830 | D2902: 296894763340
B2903: PIT.HM | C2903: 44196 | D2903: 333124108976
B2904: PIT.HM | C2904: 44561 | D2904: 329595165601
B2905: PIT.HM | C2905: 44926 | D2905: 272449745684
B2906: PIT.HM | C2906: 45291 | D2906: 285929063442
... B2991: VHC.HM | C2991: 45657 | D2991: 12234180221537
B2992: VC7.HN | C2992: 43830 | D2992: NULL
B2993: VC7.HN | C2993: 44196 | D2993: 463554236556
B2994: VC7.HN | C2994: 44561 | D2994: 763804630784
B2995: VC7.HN | C2995: 44926 | D2995: 840676220915
B2996: VC7.HN | C2996: 45291 | D2996: 1489039778365
B2997: VC7.HN | C2997: 45657 | D2997: 1489920209335
B2998: PVS.HN | C2998: 43830 | D2998: 26286532954217
B2999: PVS.HN | C2999: 44196 | D2999: 26279277126937
B3000: PVS.HN | C3000: 44561 | D3000: 24844977063351
B3001: PVS.HN | C3001: 44926 | D3001: 25827771639918
B3002: PVS.HN | C3002: 45291 | D3002: 26416008810387
B3003: PVS.HN | C3003: 45657 | D3003: 34076808359015
B3004: PVI.HN | C3004: 43830 | D3004: 22086852253570
... B3536: AAM.HM | C3536: 45657 | D3536: 202353239327
B3537: DHC.HM | C3537: 43830 | D3537: NULL
B3538: DHC.HM | C3538: 44196 | D3538: 2284329017296
B3539: DHC.HM | C3539: 44561 | D3539: 2401267067536
B3540: DHC.HM | C3540: 44926 | D3540: 2882483173364
B3541: DHC.HM | C3541: 45291 | D3541: 2915097525252
B3542: DHC.HM | C3542: 45657 | D3542: 3244657641103
B3543: MDC.HN | C3543: 43830 | D3543: 1188609682308
B3544: MDC.HN | C3544: 44196 | D3544: 1481383706676
B3545: MDC.HN | C3545: 44561 | D3545: 1189111511062
B3546: MDC.HN | C3546: 44926 | D3546: 1445319916322
B3547: MDC.HN | C3547: 45291 | D3547: 1098574193791
...

Sheet NTlmNTAxMGUtMWJkNS00Nz
D3: AuditId=69791_107403491_STD_2CAC842F-913C-485B-B189-B8874EA69354
D4: AuditId=82415_107403491_STD_9BF32382-3105-42E3-862E-9A4D9DE0A102
D5: AuditId=92562_107403491_STD_C47DB7CF-D369-441F-AC2A-9A5B6571A578
D6: AuditId=59562040_107403491_STD_B94F5566-D734-4E4D-B3F0-2114155A5E1C
D7: AuditId=172268127_107403491_STD_B5470D9B-4C75-47BD-A598-1D30707F6D8A
D8: AuditId=192614935_107403491_STD_E565C324-8850-4FD0-B46D-2B9F69081D57
D9: AuditId=84584_107393580_STD_76DC990E-8B41-474E-80E2-19FA65173E0D
D10: AuditId=96303_107393580_STD_D11D48E2-E642-4D48-9003-18FBF7ED8119
D11: AuditId=109167_107393580_STD_6C5750DE-DE26-45FE-B414-E983390575C6
D12: AuditId=118742_107393580_STD_8188729F-1D90-4755-A9D9-80055338A825
D13: AuditId=128383_107393580_STD_CBF8EFB9-56F4-444B-B436-B0CD02DCA05A
D14: AuditId=137964_107393580_STD_6B491C50-4574-46A5-AAB6-631899E467AB
... D3982: AuditId=1820_117098222_STD_B19BFE22-CAD3-466D-A384-948696FCA09A

Sheet Sheet5
A1: =_xll.RDP.Data(Sheet1!$A$2:$A$696,"TR.F.TotCurrLiab","Period=FY0 Frq=FY SDate=#1 EDate=#2 CH=Fd RH=IN;periodenddate",B2,Sheet2!$A$1,Sheet2!$A$2) -> Updated at 14:23:09
D2: Total Current Liabilities
B3: CHP.HM | C3: 43830 | D3: 441506514704
B4: CHP.HM | C4: 44196 | D4: 376922719745
B5: CHP.HM | C5: 44561 | D5: 325325368538
B6: CHP.HM | C6: 44926 | D6: 458135420679
B7: CHP.HM | C7: 45291 | D7: 433121421760
B8: CHP.HM | C8: 45657 | D8: 321564471202
B9: V21.HN | C9: 43830 | D9: 299141323687
B10: V21.HN | C10: 44196 | D10: 281427582779
B11: V21.HN | C11: 44561 | D11: 188845815222
B12: V21.HN | C12: 44926 | D12: 174960379061
B13: V21.HN | C13: 45291 | D13: 181715224555
B14: V21.HN | C14: 45657 | D14: 224883909674
... B302: SHP.HM | C302: 45657 | D302: 105775522508
B303: NVB.HN | D303: NULL
B304: PTL.HM | C304: 43830 | D304: 369186744962
B305: PTL.HM | C305: 44196 | D305: 398568412145
B306: PTL.HM | C306: 44561 | D306: 300683928638
B307: PTL.HM | C307: 44926 | D307: 137575553242
B308: PTL.HM | C308: 45291 | D308: 140281598495
B309: PTL.HM | C309: 45657 | D309: 597128848166
B310: HVX.HM | C310: 43830 | D310: 269061885523
B311: HVX.HM | C311: 44196 | D311: 312348071526
B312: HVX.HM | C312: 44561 | D312: 308093966749
B313: HVX.HM | C313: 44926 | D313: 327653679852
B314: HVX.HM | C314: 45291 | D314: 315858806833
B315: HVX.HM | C315: 45657 | D315: 267598746210
... B549: D11.HN | C549: 45657 | D549: 154970593808
B550: PTI.HN | D550: NULL
B551: CCL.HM | C551: 43830 | D551: 348980525491
B552: CCL.HM | C552: 44196 | D552: 468156648089
B553: CCL.HM | C553: 44561 | D553: 500184170503
B554: CCL.HM | C554: 44926 | D554: 511573094915
B555: CCL.HM | C555: 45291 | D555: 256612543477
B556: CCL.HM | C556: 45657 | D556: 276933522264
B557: C47.HM | C557: 43830 | D557: 1094274594254
B558: C47.HM | C558: 44196 | D558: 992932767542
B559: C47.HM | C559: 44561 | D559: 811501480617
B560: C47.HM | C560: 44926 | D560: 886933657193
B561: C47.HM | C561: 45291 | D561: 1038829167189
B562: C47.HM | C562: 45657 | D562: 996452578322
... B582: JVC.HM | C582: 44286 | D582: 156440989480
B583: JVC.HM | C583: 44926 | D583: NULL
B584: JVC.HM | C584: 44926 | D584: NULL
B585: JVC.HM | C585: 45291 | D585: 185095814436
B586: JVC.HM | C586: 45657 | D586: 288286032550
B587: PTB.HM | C587: 43830 | D587: 2252696590423
B588: PTB.HM | C588: 44196 | D588: 2462277650960
B589: PTB.HM | C589: 44561 | D589: 2664558119123
B590: PTB.HM | C590: 44926 | D590: 2310100111327
B591: PTB.HM | C591: 45291 | D591: 2352427924624
B592: PTB.HM | C592: 45657 | D592: 2351623639078
B593: CIG.HM | C593: 43830 | D593: 471533300858
B594: CIG.HM | C594: 44196 | D594: 438131538787
B595: CIG.HM | C595: 44561 | D595: 443794049224
B596: CIG.HM | C596: 44926 | D596: 567454061663
... B628: IVS.HN | C628: 45657 | D628: 136020101082
B629: PGI.HM | D629: NULL
B630: BIC.HM | D630: NULL
B631: L14.HN | C631: 43830 | D631: 78389825453
B632: L14.HN | C632: 44196 | D632: 162817766638
B633: L14.HN | C633: 44561 | D633: 179623312000
B634: L14.HN | C634: 44926 | D634: 152011479397
B635: L14.HN | C635: 45291 | D635: 225120961695
B636: L14.HN | C636: 45657 | D636: 189959914411
B637: GMX.HN | C637: 43830 | D637: 45248995274
B638: GMX.HN | C638: 44196 | D638: 47061897719
B639: GMX.HN | C639: 44561 | D639: 45446514493
B640: GMX.HN | C640: 44926 | D640: 70741849301
B641: GMX.HN | C641: 45291 | D641: 47169614854
B642: GMX.HN | C642: 45657 | D642: 43108233249
... B654: PPE.HN | C654: 45657 | D654: 2548737107
B655: MBB.HM | D655: NULL
B656: CNG.HM | C656: 43830 | D656: 278016395438
B657: CNG.HM | C657: 44196 | D657: 534554924112
B658: CNG.HM | C658: 44561 | D658: 578883645903
B659: CNG.HM | C659: 44926 | D659: 639710952445
B660: CNG.HM | C660: 45291 | D660: 529158871282
B661: CNG.HM | C661: 45657 | D661: 714563560756
B662: BRC.HM | C662: 43830 | D662: 65040980238
B663: BRC.HM | C663: 44196 | D663: 87426873676
B664: BRC.HM | C664: 44561 | D664: 99808466453
B665: BRC.HM | C665: 44926 | D665: 98933269429
B666: BRC.HM | C666: 45291 | D666: 80799953036
B667: BRC.HM | C667: 45657 | D667: 96508881762
... B805: PVB.HN | C805: 45657 | D805: 68784804743
B806: BID.HM | D806: NULL
B807: NFC.HN | C807: 43830 | D807: 54776689582
B808: NFC.HN | C808: 44196 | D808: 60057235735
B809: NFC.HN | C809: 44561 | D809: 52583640190
B810: NFC.HN | C810: 44926 | D810: 122222464260
B811: NFC.HN | C811: 45291 | D811: 84979348158
B812: NFC.HN | C812: 45657 | D812: 127216698712
B813: SCI.HN | C813: 43830 | D813: 753285097453
B814: SCI.HN | C814: 44196 | D814: 2197168878768
B815: SCI.HN | C815: 44561 | D815: 1551234563384
B816: SCI.HN | C816: 44926 | D816: 833143342987
B817: SCI.HN | C817: 45291 | D817: 1078327457689
B818: SCI.HN | C818: 45657 | D818: 1080745269590
...

Sheet ODBjNjhlNDEtMzU2Yy00MG

Sheet NGFkZGMwODUtN2E2OC00N2
D3: AuditId=69784_107403491_STD_3963666A-6824-4AF6-AECA-B62E2BA4D479
D4: AuditId=82406_107403491_STD_9B7E228C-30CC-47A9-BF23-D89134DA4202
D5: AuditId=92538_107403491_STD_C1A1EB2F-8C68-4AFC-B7DB-C388BB41A9D4
D6: AuditId=59562009_107403491_STD_B94F5566-D734-4E4D-B3F0-2114155A5E1C
D7: AuditId=172268099_107403491_STD_B5470D9B-4C75-47BD-A598-1D30707F6D8A
D8: AuditId=192614916_107403491_STD_E565C324-8850-4FD0-B46D-2B9F69081D57
D9: AuditId=84577_107393580_STD_76DC990E-8B41-474E-80E2-19FA65173E0D
D10: AuditId=96297_107393580_STD_4584CB4A-AD7A-40A7-936A-AF5C3F599EBE
D11: AuditId=109136_107393580_STD_6C5750DE-DE26-45FE-B414-E983390575C6
D12: AuditId=118715_107393580_STD_8188729F-1D90-4755-A9D9-80055338A825
D13: AuditId=128357_107393580_STD_CBF8EFB9-56F4-444B-B436-B0CD02DCA05A
D14: AuditId=137954_107393580_STD_04E438C3-0EEB-40CE-974A-6D0816599776
... D4137: AuditId=1804_117098222_STD_B19BFE22-CAD3-466D-A384-948696FCA09A

Sheet Sheet7
A1: =_xll.RDP.Data(Sheet1!$A$2:$A$696,"TR.EPSMean","Period=FY0 Frq=FY SDate=#1 EDate=#2 CH=Fd RH=IN;periodenddate",B2,Sheet2!$A$1,Sheet2!$A$2) -> Updated at 14:23:26
D2: Earnings Per Share - Mean
B3: CHP.HM | D3: NULL
B4: V21.HN | D4: NULL
B5: LIG.HN | D5: NULL
B6: MCC.HN | D6: NULL
B7: TET.HN | D7: NULL
B8: KSD.HN | D8: NULL
B9: NBW.HN | D9: NULL
B10: TDC.HM | D10: NULL
B11: OGC.HM | D11: NULL
B12: HTC.HN | D12: NULL
B13: NVT.HM | D13: NULL
B14: VCM.HN | D14: NULL
... B18: HU1.HM | D18: NULL
B19: SBA.HM | C19: 43830 | D19: 1.375
B20: IDV.HN | D20: NULL
B21: AME.HN | D21: NULL
B22: DTL.HM | D22: NULL
B23: GDW.HN | D23: NULL
B24: PDN.HM | D24: NULL
B25: NNC.HM | D25: NULL
B26: DLG.HM | D26: NULL
B27: CMV.HM | D27: NULL
B28: VE3.HN | D28: NULL
B29: BCE.HM | D29: NULL
B30: DC2.HN | D30: NULL
B31: ORS.HM | D31: NULL
... B33: NHA.HM | D33: NULL
B34: AAA.HM | C34: 43830 | D34: 2110.8228
B35: AAA.HM | C35: 44196 | D35: 1664.5456
B36: AAA.HM | C36: 44561 | D36: 942
B37: AAA.HM | C37: 45291 | D37: 711
B38: HBS.HN | D38: NULL
B39: LDP.HN | D39: NULL
B40: DRH.HM | D40: NULL
B41: PSI.HN | D41: NULL
B42: SMT.HN | D42: NULL
B43: VRC.HM | D43: NULL
B44: HMH.HN | D44: NULL
B45: PDR.HM | C45: 45657 | D45: 778.70377
B46: VLA.HN | D46: NULL
B47: PCT.HN | D47: NULL
B48: QCG.HM | D48: NULL
B49: WCS.HN | D49: NULL
B50: SMB.HM | D50: NULL
B51: NET.HN | D51: NULL
B52: IDJ.HN | D52: NULL
B53: VOS.HM | D53: NULL
B54: SPC.HN | D54: NULL
B55: SHP.HM | D55: NULL
B56: NVB.HN | D56: NULL
B57: PTL.HM | D57: NULL
... B64: SMA.HM | D64: NULL
B65: ELC.HM | C65: 44926 | D65: 555.29383
B66: DSN.HM | D66: NULL
B67: HQC.HM | D67: NULL
B68: TDW.HM | D68: NULL
B69: ARM.HN | D69: NULL
B70: SCR.HM | D70: NULL
B71: CMX.HM | D71: NULL
B72: LM8.HM | D72: NULL
B73: LCD.HN | D73: NULL
B74: PRC.HN | D74: NULL
B75: CMS.HN | D75: NULL
B76: VNF.HN | D76: NULL
B77: EVE.HM | D77: NULL
... B91: PTD.HN | D91: NULL
B92: NKG.HM | C92: 43830 | D92: 161.75358
B93: NKG.HM | C93: 44196 | D93: 636.73563
B94: NKG.HM | C94: 44561 | D94: 6743.8256
B95: NKG.HM | C95: 44926 | D95: 2333.536
B96: NKG.HM | C96: 45291 | D96: 722.92486
B97: NKG.HM | C97: 45657 | D97: 1855.6157
B98: TSB.HN | D98: NULL
B99: VCF.HM | D99: NULL
B100: MCF.HN | D100: NULL
B101: VCA.HM | D101: NULL
B102: D11.HN | D102: NULL
B103: PTI.HN | D103: NULL
B104: CCL.HM | D104: NULL
B105: C47.HM | D105: NULL
B106: DIH.HN | D106: NULL
B107: NDN.HN | D107: NULL
B108: IDI.HM | D108: NULL
B109: JVC.HM | D109: NULL
B110: PTB.HM | C110: 43830 | D110: 6083.1529
B111: PTB.HM | C111: 44196 | D111: 5005.62
B112: PTB.HM | C112: 44561 | D112: 7234.2909
B113: PTB.HM | C113: 44926 | D113: 6911
B114: PTB.HM | C114: 45291 | D114: 4549
B115: PTB.HM | C115: 45657 | D115: 5646
B116: CIG.HM | D116: NULL
B117: INC.HN | D117: NULL
B118: BSI.HM | D118: NULL
B119: THG.HM | D119: NULL
B120: SVN.HN | D120: NULL
B121: IVS.HN | D121: NULL
B122: PGI.HM | D122: NULL
B123: BIC.HM | D123: NULL
...

Sheet Sheet9
A1: =_xll.RDP.Data(Sheet1!$A$2:$A$696,"TR.F.ComEqTot","Period=FY0 Frq=FY SDate=#1 EDate=#2 CH=Fd RH=IN;periodenddate",B2,Sheet2!$A$1,Sheet2!$A$2) -> Updated at 14:27:11
D2: Common Equity - Total
B3: CHP.HM | C3: 43830 | D3: 1764242810870
B4: CHP.HM | C4: 44196 | D4: 1893861790283
B5: CHP.HM | C5: 44561 | D5: 1894194143805
B6: CHP.HM | C6: 44926 | D6: 1997177349845
B7: CHP.HM | C7: 45291 | D7: 1938518281144
B8: CHP.HM | C8: 45657 | D8: 1987895836165
B9: V21.HN | C9: 43830 | D9: 115665195633
B10: V21.HN | C10: 44196 | D10: 117203737081
B11: V21.HN | C11: 44561 | D11: 120917661403
B12: V21.HN | C12: 44926 | D12: 121846546191
B13: V21.HN | C13: 45291 | D13: 121905554149
B14: V21.HN | C14: 45657 | D14: 120729487924
... B592: JVC.HM | C592: 44286 | D592: 454692353573
B593: JVC.HM | C593: 44926 | D593: NULL
B594: JVC.HM | C594: 44926 | D594: NULL
B595: JVC.HM | C595: 45291 | D595: 499149237891
B596: JVC.HM | C596: 45657 | D596: 539431468685
B597: PTB.HM | C597: 43830 | D597: 1784503605222
B598: PTB.HM | C598: 44196 | D598: 1922878997099
B599: PTB.HM | C599: 44561 | D599: 2320430347266
B600: PTB.HM | C600: 44926 | D600: 2687241541830
B601: PTB.HM | C601: 45291 | D601: 2723503357061
B602: PTB.HM | C602: 45657 | D602: 2903296701880
B603: CIG.HM | C603: 43830 | D603: 203400328673
B604: CIG.HM | C604: 44196 | D604: 27617307756
B605: CIG.HM | C605: 44561 | D605: 43311840474
B606: CIG.HM | C606: 44926 | D606: 33959901357
... B1685: ICT.HM | C1685: 45657 | D1685: 656220180343
B1686: NO1.HM | D1686: Unable to collect data for the field 'TR.F.ComEqTot' and some specific identifier(s).
B1687: PCH.HN | C1687: 43830 | D1687: 148503144757
B1688: PCH.HN | C1688: 44196 | D1688: 185910049438
B1689: PCH.HN | C1689: 44561 | D1689: 190426392294
B1690: PCH.HN | C1690: 44926 | D1690: 233406045406
B1691: PCH.HN | C1691: 45291 | D1691: 245196649553
B1692: PCH.HN | C1692: 45657 | D1692: 257604910879
B1693: DVM.HN | C1693: 44196 | D1693: 211557638624
B1694: DVM.HN | C1694: 44561 | D1694: 440622348826
B1695: DVM.HN | C1695: 44926 | D1695: 648230535183
B1696: DVM.HN | C1696: 45291 | D1696: 688672122471
B1697: DVM.HN | C1697: 45657 | D1697: 736547007127
B1698: CAR.HN | C1698: 45291 | D1698: 42657892634
... B1763: DXS.HM | C1763: 45657 | D1763: 6012271945573
B1764: CST.HN | C1764: 44196 | D1764: NULL
B1765: CST.HN | C1765: 44561 | D1765: 744503689020
B1766: CST.HN | C1766: 44926 | D1766: 982096380128
B1767: CST.HN | C1767: 45291 | D1767: 1103840359346
B1768: CST.HN | C1768: 45657 | D1768: 1070587112584
B1769: SCG.HN | C1769: 43830 | D1769: 105377474092
B1770: SCG.HN | C1770: 44196 | D1770: 595552430285
B1771: SCG.HN | C1771: 44561 | D1771: 1107030448871
B1772: SCG.HN | C1772: 44926 | D1772: 1128143043075
B1773: SCG.HN | C1773: 45291 | D1773: 1148498295718
B1774: SCG.HN | C1774: 45657 | D1774: 1346319097981
B1775: AAT.HM | C1775: 43830 | D1775: 410895077425
B1776: AAT.HM | C1776: 44196 | D1776: 424933545217
... B2890: DPM.HM | C2890: 45657 | D2890: 11002431639788
B2891: VPL.HM | C2891: 43830 | D2891: NULL
B2892: VPL.HM | C2892: 44196 | D2892: NULL
B2893: VPL.HM | C2893: 44561 | D2893: NULL
B2894: VPL.HM | C2894: 44926 | D2894: NULL
B2895: VPL.HM | C2895: 45291 | D2895: 13314464000000
B2896: DQC.HM | C2896: 43830 | D2896: 967085217599
B2897: DQC.HM | C2897: 44196 | D2897: 914927364834
B2898: DQC.HM | C2898: 44561 | D2898: 936213961360
B2899: DQC.HM | C2899: 44926 | D2899: 922106828970
B2900: DQC.HM | C2900: 45291 | D2900: 887708221162
B2901: DQC.HM | C2901: 45657 | D2901: 765143988155
B2902: PIT.HM | C2902: 43830 | D2902: 118772273328
B2903: PIT.HM | C2903: 44196 | D2903: 120623557365
B2904: PIT.HM | C2904: 44561 | D2904: 115163754603
B2905: PIT.HM | C2905: 44926 | D2905: 118331472286
B2906: PIT.HM | C2906: 45291 | D2906: 109380365029
... B2991: VHC.HM | C2991: 45657 | D2991: 8675301054742
B2992: VC7.HN | C2992: 43830 | D2992: NULL
B2993: VC7.HN | C2993: 44196 | D2993: 259894521164
B2994: VC7.HN | C2994: 44561 | D2994: 510287002903
B2995: VC7.HN | C2995: 44926 | D2995: 518257769275
B2996: VC7.HN | C2996: 45291 | D2996: 1033777888045
B2997: VC7.HN | C2997: 45657 | D2997: 1046475557523
B2998: PVS.HN | C2998: 43830 | D2998: 12252625217993
B2999: PVS.HN | C2999: 44196 | D2999: 12145550603050
B3000: PVS.HN | C3000: 44561 | D3000: 11806182383966
B3001: PVS.HN | C3001: 44926 | D3001: 12218544502628
B3002: PVS.HN | C3002: 45291 | D3002: 12834285977444
B3003: PVS.HN | C3003: 45657 | D3003: 13568615264237
B3004: PVI.HN | C3004: 43830 | D3004: 6920851788972
... B3536: AAM.HM | C3536: 45657 | D3536: 196340095186
B3537: DHC.HM | C3537: 43830 | D3537: NULL
B3538: DHC.HM | C3538: 44196 | D3538: 1394944316463
B3539: DHC.HM | C3539: 44561 | D3539: 1697095726320
B3540: DHC.HM | C3540: 44926 | D3540: 1748355602625
B3541: DHC.HM | C3541: 45291 | D3541: 1848880199676
B3542: DHC.HM | C3542: 45657 | D3542: 2000950089755
B3543: MDC.HN | C3543: 43830 | D3543: 243243204280
B3544: MDC.HN | C3544: 44196 | D3544: 246154796865
B3545: MDC.HN | C3545: 44561 | D3545: 261269942113
B3546: MDC.HN | C3546: 44926 | D3546: 314714635421
B3547: MDC.HN | C3547: 45291 | D3547: 337968964146
...

Sheet NjU0Zjc4OGEtYmJhYi00ZT
D3: AuditId=69788_107403491_STD_C66815C1-4A2B-4993-9493-C1F5453D23CA
D4: AuditId=82413_107403491_STD_9B7E228C-30CC-47A9-BF23-D89134DA4202
D5: AuditId=92546_107403491_STD_C1A1EB2F-8C68-4AFC-B7DB-C388BB41A9D4
D6: AuditId=59562022_107403491_STD_B94F5566-D734-4E4D-B3F0-2114155A5E1C
D7: AuditId=172268091_107403491_STD_B5470D9B-4C75-47BD-A598-1D30707F6D8A
D8: AuditId=192614913_107403491_STD_E565C324-8850-4FD0-B46D-2B9F69081D57
D9: AuditId=84582_107393580_STD_76DC990E-8B41-474E-80E2-19FA65173E0D
D10: AuditId=96301_107393580_STD_4584CB4A-AD7A-40A7-936A-AF5C3F599EBE
D11: AuditId=109147_107393580_STD_6C5750DE-DE26-45FE-B414-E983390575C6
D12: AuditId=118720_107393580_STD_8188729F-1D90-4755-A9D9-80055338A825
D13: AuditId=129800_107393580_STD_802F3819-F939-4EFD-9F53-5A4BAD1B7C0D
D15: AuditId=87182_107345512_STD_7B8F1745-6942-46B4-BA25-8101F8D58C43
... D3482: AuditId=1792_117098222_STD_B19BFE22-CAD3-466D-A384-948696FCA09A

Sheet Sheet11
A1: =_xll.RDP.Data(Sheet1!$A$2:$A$696,"TR.F.DebtLTTot","Period=FY0 Frq=FY SDate=#1 EDate=#2 CH=Fd RH=IN;periodenddate",B2,Sheet2!$A$1,Sheet2!$A$2) -> Updated at 14:29:33
D2: Debt - Long-Term - Total
B3: CHP.HM | C3: 43830 | D3: 1405923585411
B4: CHP.HM | C4: 44196 | D4: 1261980213579
B5: CHP.HM | C5: 44561 | D5: 1053183946200
B6: CHP.HM | C6: 44926 | D6: 804387678831
B7: CHP.HM | C7: 45291 | D7: 595591411447
B8: CHP.HM | C8: 45657 | D8: 386789653729
B9: V21.HN | C9: 43830 | D9: 0
B10: V21.HN | C10: 44196 | D10: 25296681191
B11: V21.HN | C11: 44561 | D11: 5450899401
B12: V21.HN | C12: 44926 | D12: 0
B13: V21.HN | C13: 45291 | D13: 0
B14: V21.HN | C14: 45657 | D14: NULL
B15: LIG.HN | C15: 43830 | D15: 936187832416
B16: LIG.HN | C16: 44196 | D16: 969126200879
B17: LIG.HN | C17: 44561 | D17: 415034023563
B18: LIG.HN | C18: 44926 | D18: 716910955913
B19: LIG.HN | C19: 45291 | D19: 874333144747
B20: LIG.HN | C20: 45657 | D20: 827364761746
B21: MCC.HN | D21: NULL
B22: TET.HN | D22: NULL
B23: KSD.HN | D23: NULL
B24: NBW.HN | D24: NULL
B25: TDC.HM | C25: 43830 | D25: 317479278638
B26: TDC.HM | C26: 44196 | D26: 861867141342
B27: TDC.HM | C27: 44561 | D27: 801192893344
B28: TDC.HM | C28: 44926 | D28: 687423183336
B29: TDC.HM | C29: 45291 | D29: 689685706000
B30: TDC.HM | C30: 45657 | D30: 152642153587
B31: OGC.HM | C31: 43830 | D31: 160031166911
B32: OGC.HM | C32: 44196 | D32: 153301588029
B33: OGC.HM | C33: 44561 | D33: 151231166911
B34: OGC.HM | C34: 44926 | D34: 132331166911
B35: OGC.HM | C35: 45291 | D35: 1532331166911
B36: OGC.HM | C36: 45657 | D36: 1270000000000
B37: HTC.HN | D37: NULL
B38: NVT.HM | C38: 43830 | D38: 8325135038
B39: NVT.HM | C39: 44196 | D39: 2775043530
B40: NVT.HM | C40: 44561 | D40: 295117064809
B41: NVT.HM | C41: 44926 | D41: 278949749683
B42: NVT.HM | C42: 45291 | D42: 250732233695
B43: NVT.HM | C43: 45657 | D43: 224197106707
B44: VCM.HN | D44: NULL
B45: SPM.HM | C45: 43830 | D45: 13306056370
B46: SPM.HM | C46: 44196 | D46: 0
B47: SPM.HM | C47: 44561 | D47: 0
B48: SPM.HM | C48: 44926 | D48: 0
B49: SPM.HM | C49: 45291 | D49: NULL
B50: SPM.HM | C50: 45657 | D50: NULL
B51: CX8.HN | D51: NULL
B52: TNT.HM | C52: 43830 | D52: 948410000
B53: TNT.HM | C53: 44196 | D53: 670850000
B54: TNT.HM | C54: 44561 | D54: 393290000
B55: TNT.HM | C55: 44926 | D55: 115730000
B56: TNT.HM | C56: 45291 | D56: 812475000000
B57: TNT.HM | C57: 45657 | D57: 760000000
B58: HU1.HM | C58: 43830 | D58: 78973989966
B59: HU1.HM | C59: 44196 | D59: 0
B60: HU1.HM | C60: 44561 | D60: 0
B61: HU1.HM | C61: 44926 | D61: NULL
B62: HU1.HM | C62: 45291 | D62: 0
B63: HU1.HM | C63: 45657 | D63: 0
B64: SBA.HM | C64: 43830 | D64: 371457408883
B65: SBA.HM | C65: 44196 | D65: 326286214456
B66: SBA.HM | C66: 44561 | D66: 263574259281
B67: SBA.HM | C67: 44926 | D67: 175210940485
B68: SBA.HM | C68: 45291 | D68: 93148548154
B69: SBA.HM | C69: 45657 | D69: 41951999998
B70: IDV.HN | C70: 44104 | D70: 23449391000
B71: IDV.HN | C71: 44469 | D71: 18849391000
B72: IDV.HN | C72: 44834 | D72: 47769391000
B73: IDV.HN | C73: 45199 | D73: 59673391000
... B80: AME.HN | C80: 45291 | D80: 0
B81: AME.HN | C81: 45657 | D81: NULL
B82: DTL.HM | C82: 43830 | D82: 42162639678
B83: DTL.HM | C83: 44196 | D83: 14072011164
B84: DTL.HM | C84: 44561 | D84: 0
B85: DTL.HM | C85: 44926 | D85: 15204992824
B86: DTL.HM | C86: 45291 | D86: 9675904528
B87: DTL.HM | C87: 45657 | D87: 4146816232
B88: GDW.HN | C88: 43830 | D88: 28180425811
B89: GDW.HN | C89: 44196 | D89: 23237761499
B90: GDW.HN | C90: 44561 | D90: 18295097227
B91: GDW.HN | C91: 44926 | D91: 13352432955
B92: GDW.HN | C92: 45291 | D92: 8409768683
B93: GDW.HN | C93: 45657 | D93: 3467104411
... B99: PDN.HM | C99: 45657 | D99: 45205000000
B100: NNC.HM | C100: 43830 | D100: NULL
B101: NNC.HM | C101: 44196 | D101: NULL
B102: NNC.HM | C102: 44561 | D102: 0
B103: NNC.HM | C103: 44926 | D103: NULL
B104: NNC.HM | C104: 45291 | D104: NULL
B105: NNC.HM | C105: 45657 | D105: 0
B106: DLG.HM | C106: 43830 | D106: 2386513327318
B107: DLG.HM | C107: 44196 | D107: 2586779223774
B108: DLG.HM | C108: 44561 | D108: 1952635810423
B109: DLG.HM | C109: 44926 | D109: 1845660795288
B110: DLG.HM | C110: 45291 | D110: 1682860795288
B111: DLG.HM | C111: 45657 | D111: 1433391403555
...

Sheet ZmIzNmI3MDAtYWMzOC00MD
D3: AuditId=69749_107403491_STD_2CAC842F-913C-485B-B189-B8874EA69354
D4: AuditId=82371_107403491_STD_9BF32382-3105-42E3-862E-9A4D9DE0A102
D5: AuditId=92496_107403491_STD_C47DB7CF-D369-441F-AC2A-9A5B6571A578
D6: AuditId=59561973_107403491_STD_B94F5566-D734-4E4D-B3F0-2114155A5E1C
D7: AuditId=172268053_107403491_STD_B5470D9B-4C75-47BD-A598-1D30707F6D8A
D8: AuditId=192614871_107403491_STD_6C81D584-74D2-4A8C-8F9B-51699DB4BAA3
D9: AuditId=84539_107393580_STD_76DC990E-8B41-474E-80E2-19FA65173E0D
D10: AuditId=96263_107393580_STD_4584CB4A-AD7A-40A7-936A-AF5C3F599EBE
D11: AuditId=109108_107393580_STD_6C5750DE-DE26-45FE-B414-E983390575C6
D12: AuditId=118678_107393580_STD_8188729F-1D90-4755-A9D9-80055338A825
D13: AuditId=128327_107393580_STD_CBF8EFB9-56F4-444B-B436-B0CD02DCA05A
D14: AuditId=137910_107393580_STD_6B491C50-4574-46A5-AAB6-631899E467AB
... D3842: AuditId=1745_117098222_STD_B19BFE22-CAD3-466D-A384-948696FCA09A

Sheet Sheet13
A1: =_xll.RDP.Data(Sheet1!$A$2:$A$696,"TR.F.TradeAcctPbleAccrualsST","Period=FY0 Frq=FY SDate=#1 EDate=#2 CH=Fd RH=IN;periodenddate",B2,Sheet2!$A$1,Sheet2!$A$2) -> Updated at 14:32:18
D2: Trade Accounts Payable & Accruals - Short-Term
B3: CHP.HM | C3: 43830 | D3: 152453331212
B4: CHP.HM | C4: 44196 | D4: 45031975861
B5: CHP.HM | C5: 44561 | D5: 45260147855
B6: CHP.HM | C6: 44926 | D6: 40179336132
B7: CHP.HM | C7: 45291 | D7: 31274389649
B8: CHP.HM | C8: 45657 | D8: 36576084146
B9: V21.HN | C9: 43830 | D9: 125748551385
B10: V21.HN | C10: 44196 | D10: 162451579136
B11: V21.HN | C11: 44561 | D11: 69951315149
B12: V21.HN | C12: 44926 | D12: 62950374533
B13: V21.HN | C13: 45291 | D13: 35139737704
B14: V21.HN | C14: 45657 | D14: 54375232741
... B170: DC2.HN | C170: 45657 | D170: 60895556389
B171: ORS.HM | D171: NULL
B172: DTA.HM | C172: 43830 | D172: 2560715224
B173: DTA.HM | C173: 44196 | D173: 7634463134
B174: DTA.HM | C174: 44561 | D174: 5582035554
B175: DTA.HM | C175: 44926 | D175: 50817520184
B176: DTA.HM | C176: 45291 | D176: 22401246574
B177: DTA.HM | C177: 45657 | D177: 35642608615
B178: NHA.HM | C178: 43830 | D178: 823713347
B179: NHA.HM | C179: 44196 | D179: 25372746087
B180: NHA.HM | C180: 44561 | D180: 60746639738
B181: NHA.HM | C181: 44926 | D181: 48393255675
B182: NHA.HM | C182: 45291 | D182: 22641273245
B183: NHA.HM | C183: 45657 | D183: 24735678292
... B189: AAA.HM | C189: 45657 | D189: 1066295003739
B190: HBS.HN | D190: NULL
B191: LDP.HN | C191: 43830 | D191: 73944058401
B192: LDP.HN | C192: 44196 | D192: 45806752606
B193: LDP.HN | C193: 44561 | D193: 17308835666
B194: LDP.HN | C194: 44926 | D194: 39051027368
B195: LDP.HN | C195: 45291 | D195: 31883324170
B196: LDP.HN | C196: 45657 | D196: 47279590934
B197: DRH.HM | C197: 43830 | D197: 75681486174
B198: DRH.HM | C198: 44196 | D198: 93162670560
B199: DRH.HM | C199: 44561 | D199: 184117921585
B200: DRH.HM | C200: 44926 | D200: 224193766998
B201: DRH.HM | C201: 45291 | D201: 323927162631
B202: DRH.HM | C202: 45657 | D202: 555330481315
B203: PSI.HN | D203: NULL
B204: SMT.HN | C204: 43830 | D204: 41635373447
B205: SMT.HN | C205: 44196 | D205: 58150727201
B206: SMT.HN | C206: 44561 | D206: 118901653550
B207: SMT.HN | C207: 44926 | D207: 21822054023
B208: SMT.HN | C208: 45291 | D208: 13219819491
B209: SMT.HN | C209: 45657 | D209: 1.0757774e+10
B210: VRC.HM | C210: 43830 | D210: 7001235880
B211: VRC.HM | C211: 44196 | D211: 6140393242
B212: VRC.HM | C212: 44561 | D212: 6260526554
B213: VRC.HM | C213: 44926 | D213: 27154343673
B214: VRC.HM | C214: 45291 | D214: 26170645181
B215: VRC.HM | C215: 45657 | D215: 25349221211
... B287: SHP.HM | C287: 45657 | D287: 21027342129
B288: NVB.HN | D288: NULL
B289: PTL.HM | C289: 43830 | D289: 167326674408
B290: PTL.HM | C290: 44196 | D290: 136176787752
B291: PTL.HM | C291: 44561 | D291: 51276955316
B292: PTL.HM | C292: 44926 | D292: 111754003103
B293: PTL.HM | C293: 45291 | D293: 52862238619
B294: PTL.HM | C294: 45657 | D294: 245512630173
B295: HVX.HM | C295: 43830 | D295: 151253649562
B296: HVX.HM | C296: 44196 | D296: 119322308865
B297: HVX.HM | C297: 44561 | D297: 118549111493
B298: HVX.HM | C298: 44926 | D298: 200168265211
B299: HVX.HM | C299: 45291 | D299: 164499925928
B300: HVX.HM | C300: 45657 | D300: 147841594261
... B534: D11.HN | C534: 45657 | D534: 83788939497
B535: PTI.HN | D535: NULL
B536: CCL.HM | C536: 43830 | D536: 64466247997
B537: CCL.HM | C537: 44196 | D537: 55281138845
B538: CCL.HM | C538: 44561 | D538: 100010703887
B539: CCL.HM | C539: 44926 | D539: 82576551377
B540: CCL.HM | C540: 45291 | D540: 36555402382
B541: CCL.HM | C541: 45657 | D541: 44950275063
B542: C47.HM | C542: 43830 | D542: 276302431528
B543: C47.HM | C543: 44196 | D543: 299825963103
B544: C47.HM | C544: 44561 | D544: 128439995808
B545: C47.HM | C545: 44926 | D545: 188152425496
B546: C47.HM | C546: 45291 | D546: 325773036912
B547: C47.HM | C547: 45657 | D547: 273823292105
... B567: JVC.HM | C567: 44286 | D567: 65263947950
B568: JVC.HM | C568: 44926 | D568: NULL
B569: JVC.HM | C569: 44926 | D569: NULL
B570: JVC.HM | C570: 45291 | D570: 73136297402
B571: JVC.HM | C571: 45657 | D571: 103689657580
B572: PTB.HM | C572: 43830 | D572: 544553165075
B573: PTB.HM | C573: 44196 | D573: 663359974979
B574: PTB.HM | C574: 44561 | D574: 769055052952
B575: PTB.HM | C575: 44926 | D575: 578973208491
B576: PTB.HM | C576: 45291 | D576: 676622562018
B577: PTB.HM | C577: 45657 | D577: 724102486565
B578: CIG.HM | C578: 43830 | D578: 127615410379
B579: CIG.HM | C579: 44196 | D579: 127856427867
B580: CIG.HM | C580: 44561 | D580: 129084826529
B581: CIG.HM | C581: 44926 | D581: 286513254671
... B589: INC.HN | C589: 45657 | D589: 4971666371
B590: BSI.HM | D590: NULL
...

Sheet N2IzMDU2YzktYTdhYS00YW
D5: AuditId=87135_107345512_STD_7B8F1745-6942-46B4-BA25-8101F8D58C43
D6: AuditId=100296_107345512_STD_C335E499-4FAD-4A3C-BEE3-7E40058F9E0E
D7: AuditId=115210_107345512_STD_EC5F40F5-6786-4665-AEFA-A17A2C0BEB2F
D8: AuditId=126052_107345512_STD_C5C6F882-0625-4D02-8D51-B637A286169C
D9: AuditId=137030_107345512_STD_A3689EC0-86B0-44B8-8A5D-A95202961498
D10: AuditId=148230_107345512_STD_740CA875-3E53-498F-B93C-9A2072BC6A88
D16: AuditId=115809_107408462_STD_AF3885ED-00A5-41FA-9D46-840A49F8456C
D17: AuditId=113746_107408462_STD_8C401689-43FD-49DD-86E9-4F3007BE6DE8
D18: AuditId=80559859_107408462_STD_317CECBF-6549-4EA0-94C1-1F0307CB6BB1
D19: AuditId=57915060_107408462_STD_84D91A2D-0CB4-4F49-BD26-DF05040A8CBB
D20: AuditId=167193384_107408462_STD_3C30F9C7-4855-42D7-B71B-7F29953A0B34
D21: AuditId=240869811_107408462_STD_EC49933E-D98F-44A5-B8ED-BE9B8F9995C0
... D1408: AuditId=1750_117098222_STD_B19BFE22-CAD3-466D-A384-948696FCA09A

Sheet Sheet15
A1: =_xll.RDP.Data(Sheet1!$A$2:$A$696,"TR.F.AcctPbleInclAccrExpnLT","Period=FY0 Frq=FY SDate=#1 EDate=#2 CH=Fd RH=IN;periodenddate",B2,Sheet2!$A$1,Sheet2!$A$2) -> Updated at 14:33:08
D2: Accounts Payable including Accrued Expenses - Long-Term
B3: CHP.HM | D3: NULL
B4: V21.HN | D4: NULL
B5: LIG.HN | C5: 43830 | D5: 77221962098
B6: LIG.HN | C6: 44196 | D6: 237914623985
B7: LIG.HN | C7: 44561 | D7: 282356892576
B8: LIG.HN | C8: 44926 | D8: 318343054689
B9: LIG.HN | C9: 45291 | D9: 237684594235
B10: LIG.HN | C10: 45657 | D10: 111583365094
B11: MCC.HN | D11: NULL
B12: TET.HN | D12: NULL
B13: KSD.HN | D13: NULL
B14: NBW.HN | D14: NULL
B15: TDC.HM | D15: NULL
B16: OGC.HM | C16: 43830 | D16: 41320839176
B17: OGC.HM | C17: 44196 | D17: 3922928954
B18: OGC.HM | C18: 44561 | D18: 3922928954
B19: OGC.HM | C19: 44926 | D19: 3922928954
B20: OGC.HM | C20: 45291 | D20: 3363621314
B21: OGC.HM | C21: 45657 | D21: 2625664458
B22: HTC.HN | D22: NULL
B23: NVT.HM | D23: NULL
B24: VCM.HN | D24: NULL
B25: SPM.HM | D25: NULL
B26: CX8.HN | D26: NULL
B27: TNT.HM | C27: 43830 | D27: NULL
B28: TNT.HM | C28: 44196 | D28: NULL
B29: TNT.HM | C29: 44561 | D29: NULL
B30: TNT.HM | C30: 44926 | D30: NULL
B31: TNT.HM | C31: 45291 | D31: 27271089917
B32: TNT.HM | C32: 45657 | D32: 0
B33: HU1.HM | D33: NULL
B34: SBA.HM | D34: NULL
B35: IDV.HN | D35: NULL
B36: AME.HN | C36: 43830 | D36: NULL
B37: AME.HN | C37: 44196 | D37: NULL
B38: AME.HN | C38: 44561 | D38: 0
B39: AME.HN | C39: 44926 | D39: 0
B40: AME.HN | C40: 45291 | D40: NULL
B41: AME.HN | C41: 45657 | D41: NULL
B42: DTL.HM | D42: NULL
B43: GDW.HN | D43: NULL
B44: PDN.HM | D44: NULL
B45: NNC.HM | D45: NULL
B46: DLG.HM | C46: 43830 | D46: 1762792456
B47: DLG.HM | C47: 44196 | D47: 13366626818
B48: DLG.HM | C48: 44561 | D48: NULL
B49: DLG.HM | C49: 44926 | D49: NULL
B50: DLG.HM | C50: 45291 | D50: NULL
B51: DLG.HM | C51: 45657 | D51: NULL
B52: CMV.HM | D52: NULL
B53: VE3.HN | C53: 43830 | D53: NULL
B54: VE3.HN | C54: 44196 | D54: NULL
B55: VE3.HN | C55: 44561 | D55: 1146762171
B56: VE3.HN | C56: 44926 | D56: 863566898
B57: VE3.HN | C57: 45291 | D57: 409683406
B58: VE3.HN | C58: 45657 | D58: 409683406
B59: BCE.HM | C59: 43830 | D59: 0
B60: BCE.HM | C60: 44196 | D60: 0
B61: BCE.HM | C61: 44561 | D61: NULL
B62: BCE.HM | C62: 44926 | D62: NULL
B63: BCE.HM | C63: 45291 | D63: NULL
B64: BCE.HM | C64: 45657 | D64: NULL
B65: DC2.HN | D65: NULL
B66: ORS.HM | D66: NULL
B67: DTA.HM | D67: NULL
B68: NHA.HM | D68: NULL
B69: AAA.HM | C69: 43830 | D69: NULL
B70: AAA.HM | C70: 44196 | D70: 25253997253
B71: AAA.HM | C71: 44561 | D71: 887312160
B72: AAA.HM | C72: 44926 | D72: 7806045831
B73: AAA.HM | C73: 45291 | D73: 0
B74: AAA.HM | C74: 45657 | D74: NULL
B75: HBS.HN | D75: NULL
B76: LDP.HN | D76: NULL
B77: DRH.HM | D77: NULL
B78: PSI.HN | D78: NULL
B79: SMT.HN | D79: NULL
B80: VRC.HM | D80: NULL
B81: HMH.HN | D81: NULL
B82: PDR.HM | C82: 43830 | D82: NULL
B83: PDR.HM | C83: 44196 | D83: NULL
B84: PDR.HM | C84: 44561 | D84: 274000000000
B85: PDR.HM | C85: 44926 | D85: NULL
B86: PDR.HM | C86: 45291 | D86: NULL
B87: PDR.HM | C87: 45657 | D87: NULL
B88: VLA.HN | D88: NULL
B89: PCT.HN | D89: NULL
B90: QCG.HM | D90: NULL
B91: WCS.HN | D91: NULL
B92: SMB.HM | D92: NULL
B93: NET.HN | D93: NULL
B94: IDJ.HN | D94: NULL
B95: VOS.HM | D95: NULL
B96: SPC.HN | D96: NULL
B97: SHP.HM | D97: NULL
B98: NVB.HN | D98: NULL
B99: PTL.HM | D99: NULL
B100: HVX.HM | C100: 43830 | D100: 157400000000
...

Sheet OWY5NTFhZjktYWIwNy00OT
D95: AuditId=87456_106151713_STD_E5AB4070-504D-49E3-B476-DD99295789AF
D96: AuditId=99770_106151713_STD_E5AB4070-504D-49E3-B476-DD99295789AF
D97: AuditId=113883_106151713_STD_F73303BB-ACF0-479D-AA05-E38063B5DFE9
D98: AuditId=124059_106151713_STD_CF8FF8A5-B18A-44BA-85A3-60B97046B7B2
D99: AuditId=136073606_106151713_STD_35A4E005-6817-47C1-A333-5ABF7F8BE98A
D100: AuditId=250813083_106151713_STD_DAA05BC2-A77E-415C-BFBE-C8E45708E001
D114: AuditId=69420_110243153_STD_58D85CC3-E754-43DF-8143-DAFEF270B813
D115: AuditId=81268_110243153_STD_9BCF2486-21E1-4012-ADBC-F60F2C314713
D116: AuditId=93299_110243153_STD_00506DA0-88A1-4689-9B72-907F0213CF5B
D117: AuditId=21516356_110243153_STD_D76DE1CF-C458-43DF-9D94-25FA7E02DA15
D118: AuditId=154415020_110243153_STD_911B972A-5735-4F84-B1E1-72B6A7B887C3
D119: AuditId=217784404_110243153_STD_622D558E-DFFE-4754-AFAF-FF244200F827
... D635: AuditId=221829730_103854723_STD_320A30A9-E799-43EE-8296-45C43C2E64E4

Sheet Sheet17
A1: =_xll.RDP.Data(Sheet1!$A$2:$A$696,"TR.F.RcvblTot","Period=FY0 Frq=FY SDate=#1 EDate=#2 CH=Fd RH=IN;periodenddate",B2,Sheet2!$A$1,Sheet2!$A$2) -> Updated at 14:34:35
D2: Receivables - Total
B3: CHP.HM | D3: NULL
B4: V21.HN | D4: NULL
B5: LIG.HN | D5: NULL
B6: MCC.HN | D6: NULL
B7: TET.HN | D7: NULL
B8: KSD.HN | D8: NULL
B9: NBW.HN | D9: NULL
B10: TDC.HM | D10: NULL
B11: OGC.HM | D11: NULL
B12: HTC.HN | D12: NULL
B13: NVT.HM | D13: NULL
B14: VCM.HN | D14: NULL
... B94: D11.HN | D94: NULL
B95: PTI.HN | C95: 43830 | D95: 936784381813
B96: PTI.HN | C96: 44196 | D96: 772343505096
B97: PTI.HN | C97: 44561 | D97: 744999838496
B98: PTI.HN | C98: 44926 | D98: 779482009172
B99: PTI.HN | C99: 45291 | D99: 677734680980
B100: PTI.HN | C100: 45657 | D100: 764139870188
B101: CCL.HM | D101: NULL
B102: C47.HM | D102: NULL
B103: DIH.HN | D103: NULL
B104: NDN.HN | D104: NULL
B105: IDI.HM | D105: NULL
B106: JVC.HM | D106: NULL
B107: PTB.HM | D107: NULL
B108: CIG.HM | D108: NULL
B109: INC.HN | D109: NULL
B110: BSI.HM | D110: NULL
B111: THG.HM | D111: NULL
B112: SVN.HN | D112: NULL
B113: IVS.HN | D113: NULL
B114: PGI.HM | C114: 43830 | D114: 571057291328
B115: PGI.HM | C115: 44196 | D115: 451875824208
B116: PGI.HM | C116: 44561 | D116: 476206031616
B117: PGI.HM | C117: 44926 | D117: 460297429868
B118: PGI.HM | C118: 45291 | D118: 623387145100
B119: PGI.HM | C119: 45657 | D119: 675498335016
B120: BIC.HM | C120: 43830 | D120: 456130452546
B121: BIC.HM | C121: 44196 | D121: 579464769494
B122: BIC.HM | C122: 44561 | D122: 447705962479
B123: BIC.HM | C123: 44926 | D123: 465120544037
B124: BIC.HM | C124: 45291 | D124: 466746046228
B125: BIC.HM | C125: 45657 | D125: 503080944632
B126: L14.HN | D126: NULL
B127: GMX.HN | D127: NULL
B128: SVT.HM | D128: NULL
B129: PPE.HN | D129: NULL
B130: MBB.HM | D130: NULL
B131: CNG.HM | D131: NULL
B132: BRC.HM | D132: NULL
B133: HHS.HM | D133: NULL
B134: GSP.HM | D134: NULL
B135: AMC.HN | D135: NULL
B136: LAS.HN | D136: NULL
B137: DRL.HM | D137: NULL
... B252: C69.HN | D252: NULL
B253: MIG.HM | C253: 43830 | D253: 569992139888
B254: MIG.HM | C254: 44196 | D254: 374772349451
B255: MIG.HM | C255: 44561 | D255: 371956636099
B256: MIG.HM | C256: 44926 | D256: 680356639097
B257: MIG.HM | C257: 45291 | D257: 446369158977
B258: MIG.HM | C258: 45657 | D258: 362189056491
B259: SBV.HM | D259: NULL
B260: TCD.HM | D260: NULL
B261: CTF.HM | D261: NULL
B262: TNI.HM | D262: NULL
B263: TTT.HN | D263: NULL
B264: EVG.HM | D264: NULL
B265: HTG.HM | D265: NULL
B266: TDG.HM | D266: NULL
B267: HII.HM | D267: NULL
B268: VSM.HN | D268: NULL
B269: VCI.HM | D269: NULL
B270: TVT.HM | D270: NULL
... B327: BKG.HM | D327: NULL
B328: PRE.HN | C328: 43830 | D328: 597356922010
B329: PRE.HN | C329: 44196 | D329: 439893781626
B330: PRE.HN | C330: 44561 | D330: 425008124001
B331: PRE.HN | C331: 44926 | D331: 501969658338
B332: PRE.HN | C332: 45291 | D332: 561009651362
B333: PRE.HN | C333: 45657 | D333: 678022058279
B334: MSB.HM | D334: NULL
B335: MCM.HM | D335: NULL
B336: GMA.HN | D336: NULL
B337: GIC.HN | D337: NULL
B338: BNA.HN | D338: NULL
B339: NAB.HM | D339: NULL
B340: ASG.HM | D340: NULL
B341: TTA.HM | D341: NULL
B342: APH.HM | D342: NULL
B343: VFS.HN | D343: NULL
B344: THD.HN | D344: NULL
B345: CKG.HM | D345: NULL
... B414: KHP.HM | D414: NULL
B415: VNR.HN | C415: 43830 | D415: 1002049866468
B416: VNR.HN | C416: 44196 | D416: 736479637994
B417: VNR.HN | C417: 44561 | D417: 774851213080
...

Sheet OThmMDI2MzgtNzhmMS00OT
D3: AuditId=69792_107403491_STD_C66815C1-4A2B-4993-9493-C1F5453D23CA
D4: AuditId=82416_107403491_STD_9B7E228C-30CC-47A9-BF23-D89134DA4202
D5: AuditId=92548_107403491_STD_C1A1EB2F-8C68-4AFC-B7DB-C388BB41A9D4
D6: AuditId=59562031_107403491_STD_B94F5566-D734-4E4D-B3F0-2114155A5E1C
D7: AuditId=172268112_107403491_STD_B5470D9B-4C75-47BD-A598-1D30707F6D8A
D8: AuditId=192614928_107403491_STD_6C81D584-74D2-4A8C-8F9B-51699DB4BAA3
D9: AuditId=84585_107393580_STD_76DC990E-8B41-474E-80E2-19FA65173E0D
D10: AuditId=96304_107393580_STD_4584CB4A-AD7A-40A7-936A-AF5C3F599EBE
D11: AuditId=109151_107393580_STD_6C5750DE-DE26-45FE-B414-E983390575C6
D12: AuditId=118734_107393580_STD_8188729F-1D90-4755-A9D9-80055338A825
D13: AuditId=128370_107393580_STD_CBF8EFB9-56F4-444B-B436-B0CD02DCA05A
D14: AuditId=137958_107393580_STD_6B491C50-4574-46A5-AAB6-631899E467AB
... D4137: AuditId=1816_117098222_STD_B19BFE22-CAD3-466D-A384-948696FCA09A

Sheet Sheet19
A1: =_xll.RDP.Data(Sheet1!$A$2:$A$696,"TR.F.LoansRcvblTot","Period=FY0 Frq=FY SDate=#1 EDate=#2 CH=Fd RH=IN;periodenddate",B2,Sheet2!$A$1,Sheet2!$A$2) -> Updated at 14:36:26
D2: Loans & Receivables - Total
B3: CHP.HM | C3: 43830 | D3: 163250952675
B4: CHP.HM | C4: 44196 | D4: 176670958189
B5: CHP.HM | C5: 44561 | D5: 296555414769
B6: CHP.HM | C6: 44926 | D6: 340267950574
B7: CHP.HM | C7: 45291 | D7: 420471811517
B8: CHP.HM | C8: 45657 | D8: 302694339604
B9: V21.HN | C9: 43830 | D9: 132753319072
B10: V21.HN | C10: 44196 | D10: 114676677460
B11: V21.HN | C11: 44561 | D11: 155095782412
B12: V21.HN | C12: 44926 | D12: 163165719683
B13: V21.HN | C13: 45291 | D13: 141265655757
B14: V21.HN | C14: 45657 | D14: 153952358635
... B592: JVC.HM | C592: 44286 | D592: 152952261073
B593: JVC.HM | C593: 44926 | D593: NULL
B594: JVC.HM | C594: 44926 | D594: NULL
B595: JVC.HM | C595: 45291 | D595: 967651587397
B596: JVC.HM | C596: 45657 | D596: 80108193142
B597: PTB.HM | C597: 43830 | D597: 885008034478
B598: PTB.HM | C598: 44196 | D598: 892455155513
B599: PTB.HM | C599: 44561 | D599: 1047833389214
B600: PTB.HM | C600: 44926 | D600: 911798529570
B601: PTB.HM | C601: 45291 | D601: 984891347415
B602: PTB.HM | C602: 45657 | D602: 1242411418618
B603: CIG.HM | C603: 43830 | D603: 392488769024
B604: CIG.HM | C604: 44196 | D604: 379196437316
B605: CIG.HM | C605: 44561 | D605: 392745420331
B606: CIG.HM | C606: 44926 | D606: 504816723345
... B1685: ICT.HM | C1685: 45657 | D1685: 615475742954
B1686: NO1.HM | D1686: Unable to collect data for the field 'TR.F.LoansRcvblTot' and some specific identifier(s).
B1687: PCH.HN | C1687: 43830 | D1687: 9046099658
B1688: PCH.HN | C1688: 44196 | D1688: 7013787069
B1689: PCH.HN | C1689: 44561 | D1689: 2812823347
B1690: PCH.HN | C1690: 44926 | D1690: 25895034938
B1691: PCH.HN | C1691: 45291 | D1691: 2703275841
B1692: PCH.HN | C1692: 45657 | D1692: 16661193010
B1693: DVM.HN | C1693: 44196 | D1693: 321209899169
B1694: DVM.HN | C1694: 44561 | D1694: 318348593906
B1695: DVM.HN | C1695: 44926 | D1695: 318265702598
B1696: DVM.HN | C1696: 45291 | D1696: 406202317232
B1697: DVM.HN | C1697: 45657 | D1697: 534177486898
B1698: CAR.HN | C1698: 45291 | D1698: 10555369355
... B1763: DXS.HM | C1763: 45657 | D1763: 8285884786153
B1764: CST.HN | C1764: 44196 | D1764: NULL
B1765: CST.HN | C1765: 44561 | D1765: 1110166552978
B1766: CST.HN | C1766: 44926 | D1766: 1143981398015
B1767: CST.HN | C1767: 45291 | D1767: 1299657296803
B1768: CST.HN | C1768: 45657 | D1768: 1142681922381
B1769: SCG.HN | C1769: 43830 | D1769: 127286746354
B1770: SCG.HN | C1770: 44196 | D1770: 632063359885
B1771: SCG.HN | C1771: 44561 | D1771: 2183297956724
B1772: SCG.HN | C1772: 44926 | D1772: 4649045319737
B1773: SCG.HN | C1773: 45291 | D1773: 4050982998670
B1774: SCG.HN | C1774: 45657 | D1774: 5438238277072
B1775: AAT.HM | C1775: 43830 | D1775: 41493644811
B1776: AAT.HM | C1776: 44196 | D1776: 115662699964
... B2890: DPM.HM | C2890: 45657 | D2890: 784708462694
B2891: VPL.HM | C2891: 43830 | D2891: NULL
B2892: VPL.HM | C2892: 44196 | D2892: NULL
B2893: VPL.HM | C2893: 44561 | D2893: NULL
B2894: VPL.HM | C2894: 44926 | D2894: NULL
B2895: VPL.HM | C2895: 45291 | D2895: 6633998000000
B2896: DQC.HM | C2896: 43830 | D2896: 433227391081
B2897: DQC.HM | C2897: 44196 | D2897: 425292181754
B2898: DQC.HM | C2898: 44561 | D2898: 358692954883
B2899: DQC.HM | C2899: 44926 | D2899: 379542659146
B2900: DQC.HM | C2900: 45291 | D2900: 457188598035
B2901: DQC.HM | C2901: 45657 | D2901: 268491304344
B2902: PIT.HM | C2902: 43830 | D2902: 96241563699
B2903: PIT.HM | C2903: 44196 | D2903: 105174471065
B2904: PIT.HM | C2904: 44561 | D2904: 127202348036
B2905: PIT.HM | C2905: 44926 | D2905: 85864786726
B2906: PIT.HM | C2906: 45291 | D2906: 103660453268
... B2991: VHC.HM | C2991: 45657 | D2991: 2084578546437
B2992: VC7.HN | C2992: 43830 | D2992: NULL
B2993: VC7.HN | C2993: 44196 | D2993: 99514308629
B2994: VC7.HN | C2994: 44561 | D2994: 251660102098
B2995: VC7.HN | C2995: 44926 | D2995: 388999070950
B2996: VC7.HN | C2996: 45291 | D2996: 977866402124
B2997: VC7.HN | C2997: 45657 | D2997: 1043803181768
B2998: PVS.HN | C2998: 43830 | D2998: 4630677387941
B2999: PVS.HN | C2999: 44196 | D2999: 5630498585355
B3000: PVS.HN | C3000: 44561 | D3000: 4665515573916
B3001: PVS.HN | C3001: 44926 | D3001: 5098601281056
B3002: PVS.HN | C3002: 45291 | D3002: 4375338492895
B3003: PVS.HN | C3003: 45657 | D3003: 6288660956413
B3004: PVI.HN | C3004: 43830 | D3004: 9940409700664
... B3536: AAM.HM | C3536: 45657 | D3536: 13787451373
B3537: DHC.HM | C3537: 43830 | D3537: NULL
B3538: DHC.HM | C3538: 44196 | D3538: 533523695852
B3539: DHC.HM | C3539: 44561 | D3539: 695672924992
B3540: DHC.HM | C3540: 44926 | D3540: 711237992879
B3541: DHC.HM | C3541: 45291 | D3541: 654861889647
B3542: DHC.HM | C3542: 45657 | D3542: 703394330560
B3543: MDC.HN | C3543: 43830 | D3543: 203459660026
B3544: MDC.HN | C3544: 44196 | D3544: 391899300015
B3545: MDC.HN | C3545: 44561 | D3545: 152405587178
B3546: MDC.HN | C3546: 44926 | D3546: 634703933676
B3547: MDC.HN | C3547: 45291 | D3547: 348726809049
...

Sheet ZWJlNjk0YWEtMmE1My00MW
D3: AuditId=69762_107403491_STD_C66815C1-4A2B-4993-9493-C1F5453D23CA
D4: AuditId=82387_107403491_STD_9BF32382-3105-42E3-862E-9A4D9DE0A102
D5: AuditId=92521_107403491_STD_C1A1EB2F-8C68-4AFC-B7DB-C388BB41A9D4
D6: AuditId=59561990_107403491_STD_B94F5566-D734-4E4D-B3F0-2114155A5E1C
D7: AuditId=172268074_107403491_STD_B5470D9B-4C75-47BD-A598-1D30707F6D8A
D8: AuditId=192614888_107403491_STD_E565C324-8850-4FD0-B46D-2B9F69081D57
D9: AuditId=84551_107393580_STD_76DC990E-8B41-474E-80E2-19FA65173E0D
D10: AuditId=96276_107393580_STD_4584CB4A-AD7A-40A7-936A-AF5C3F599EBE
D11: AuditId=109119_107393580_STD_6C5750DE-DE26-45FE-B414-E983390575C6
D12: AuditId=118696_107393580_STD_8188729F-1D90-4755-A9D9-80055338A825
D13: AuditId=128341_107393580_STD_CBF8EFB9-56F4-444B-B436-B0CD02DCA05A
D14: AuditId=137922_107393580_STD_6B491C50-4574-46A5-AAB6-631899E467AB
... D4137: AuditId=1763_117098222_STD_B19BFE22-CAD3-466D-A384-948696FCA09A

Sheet Sheet21
A1: =_xll.RDP.Data(Sheet1!$A$2:$A$696,"TR.F.CashCashEquivTot","Period=FY0 Frq=FY SDate=#1 EDate=#2 CH=Fd RH=IN;periodenddate",B2,Sheet2!$A$1,Sheet2!$A$2) -> Updated at 14:40:55
D2: Cash & Cash Equivalents - Total
B3: CHP.HM | C3: 43830 | D3: 179174174566
B4: CHP.HM | C4: 44196 | D4: 269707837090
B5: CHP.HM | C5: 44561 | D5: 91038683484
B6: CHP.HM | C6: 44926 | D6: 251256101502
B7: CHP.HM | C7: 45291 | D7: 113250882968
B8: CHP.HM | C8: 45657 | D8: 197904693647
B9: V21.HN | C9: 43830 | D9: 5738770104
B10: V21.HN | C10: 44196 | D10: 5059049245
B11: V21.HN | C11: 44561 | D11: 30211112285
B12: V21.HN | C12: 44926 | D12: 3490121694
B13: V21.HN | C13: 45291 | D13: 7360520675
B14: V21.HN | C14: 45657 | D14: 14811078411
... B592: JVC.HM | C592: 44286 | D592: 120139128350
B593: JVC.HM | C593: 44926 | D593: NULL
B594: JVC.HM | C594: 44926 | D594: NULL
B595: JVC.HM | C595: 45291 | D595: 152936802760
B596: JVC.HM | C596: 45657 | D596: 19581608627
B597: PTB.HM | C597: 43830 | D597: 126518814646
B598: PTB.HM | C598: 44196 | D598: 167783353561
B599: PTB.HM | C599: 44561 | D599: 135866626171
B600: PTB.HM | C600: 44926 | D600: 272074930811
B601: PTB.HM | C601: 45291 | D601: 428337603384
B602: PTB.HM | C602: 45657 | D602: 470850849148
B603: CIG.HM | C603: 43830 | D603: 2493226527
B604: CIG.HM | C604: 44196 | D604: 2378308561
B605: CIG.HM | C605: 44561 | D605: 916253049
B606: CIG.HM | C606: 44926 | D606: 979933550
... B1685: ICT.HM | C1685: 45657 | D1685: 429629470696
B1686: NO1.HM | D1686: Unable to collect data for the field 'TR.F.CashCashEquivTot' and some specific identifier(s).
B1687: PCH.HN | C1687: 43830 | D1687: 8596576399
B1688: PCH.HN | C1688: 44196 | D1688: 11885532811
B1689: PCH.HN | C1689: 44561 | D1689: 18490168292
B1690: PCH.HN | C1690: 44926 | D1690: 36690584484
B1691: PCH.HN | C1691: 45291 | D1691: 23916611263
B1692: PCH.HN | C1692: 45657 | D1692: 22777042455
B1693: DVM.HN | C1693: 44196 | D1693: 24308042720
B1694: DVM.HN | C1694: 44561 | D1694: 89871170714
B1695: DVM.HN | C1695: 44926 | D1695: 127602817725
B1696: DVM.HN | C1696: 45291 | D1696: 104847984669
B1697: DVM.HN | C1697: 45657 | D1697: 85716381492
B1698: CAR.HN | C1698: 45291 | D1698: 3017103939
... B1763: DXS.HM | C1763: 45657 | D1763: 416086372405
B1764: CST.HN | C1764: 44196 | D1764: NULL
B1765: CST.HN | C1765: 44561 | D1765: 826166496
B1766: CST.HN | C1766: 44926 | D1766: 686864280
B1767: CST.HN | C1767: 45291 | D1767: 642081201
B1768: CST.HN | C1768: 45657 | D1768: 800433496
B1769: SCG.HN | C1769: 43830 | D1769: 44928723399
B1770: SCG.HN | C1770: 44196 | D1770: 48400573704
B1771: SCG.HN | C1771: 44561 | D1771: 227281248385
B1772: SCG.HN | C1772: 44926 | D1772: 29472571546
B1773: SCG.HN | C1773: 45291 | D1773: 117352433699
B1774: SCG.HN | C1774: 45657 | D1774: 78072128418
B1775: AAT.HM | C1775: 43830 | D1775: 5126341358
B1776: AAT.HM | C1776: 44196 | D1776: 19726020423
... B2890: DPM.HM | C2890: 45657 | D2890: 1004912303570
B2891: VPL.HM | C2891: 43830 | D2891: NULL
B2892: VPL.HM | C2892: 44196 | D2892: NULL
B2893: VPL.HM | C2893: 44561 | D2893: NULL
B2894: VPL.HM | C2894: 44926 | D2894: NULL
B2895: VPL.HM | C2895: 45291 | D2895: 2056552000000
B2896: DQC.HM | C2896: 43830 | D2896: 150435862161
B2897: DQC.HM | C2897: 44196 | D2897: 112888328229
B2898: DQC.HM | C2898: 44561 | D2898: 56507815259
B2899: DQC.HM | C2899: 44926 | D2899: 20362653739
B2900: DQC.HM | C2900: 45291 | D2900: 22587123978
B2901: DQC.HM | C2901: 45657 | D2901: 35571943138
B2902: PIT.HM | C2902: 43830 | D2902: 5784525888
B2903: PIT.HM | C2903: 44196 | D2903: 3562559105
B2904: PIT.HM | C2904: 44561 | D2904: 9347990683
B2905: PIT.HM | C2905: 44926 | D2905: 9320762879
B2906: PIT.HM | C2906: 45291 | D2906: 1741233833
... B2991: VHC.HM | C2991: 45657 | D2991: 570012125911
B2992: VC7.HN | C2992: 43830 | D2992: NULL
B2993: VC7.HN | C2993: 44196 | D2993: 17623654577
B2994: VC7.HN | C2994: 44561 | D2994: 62890595540
B2995: VC7.HN | C2995: 44926 | D2995: 30053194451
B2996: VC7.HN | C2996: 45291 | D2996: 65465553569
B2997: VC7.HN | C2997: 45657 | D2997: 16556791348
B2998: PVS.HN | C2998: 43830 | D2998: 6949116096040
B2999: PVS.HN | C2999: 44196 | D2999: 5212155694269
B3000: PVS.HN | C3000: 44561 | D3000: 5747277411831
B3001: PVS.HN | C3001: 44926 | D3001: 5219378499294
B3002: PVS.HN | C3002: 45291 | D3002: 5757120569689
B3003: PVS.HN | C3003: 45657 | D3003: 11421530345030
B3004: PVI.HN | C3004: 43830 | D3004: 492708558335
... B3536: AAM.HM | C3536: 45657 | D3536: 62696698955
B3537: DHC.HM | C3537: 43830 | D3537: NULL
B3538: DHC.HM | C3538: 44196 | D3538: 202090986015
B3539: DHC.HM | C3539: 44561 | D3539: 98169465231
B3540: DHC.HM | C3540: 44926 | D3540: 189178341116
B3541: DHC.HM | C3541: 45291 | D3541: 247229229877
B3542: DHC.HM | C3542: 45657 | D3542: 570814931920
B3543: MDC.HN | C3543: 43830 | D3543: 3211485871
B3544: MDC.HN | C3544: 44196 | D3544: 2977184068
B3545: MDC.HN | C3545: 44561 | D3545: 4338527255
B3546: MDC.HN | C3546: 44926 | D3546: 4553316469
B3547: MDC.HN | C3547: 45291 | D3547: 3152634935
...

Sheet NDFkOTAwZDQtYWUyNS00ZW
D3: AuditId=84075_107403491_STD_9BF32382-3105-42E3-862E-9A4D9DE0A102
D4: AuditId=82689_107403491_STD_9B7E228C-30CC-47A9-BF23-D89134DA4202
D5: AuditId=59561420_107403491_STD_B94F5566-D734-4E4D-B3F0-2114155A5E1C
D6: AuditId=59562402_107403491_STD_B94F5566-D734-4E4D-B3F0-2114155A5E1C
D7: AuditId=192616546_107403491_STD_6C81D584-74D2-4A8C-8F9B-51699DB4BAA3
D8: AuditId=192615196_107403491_STD_E565C324-8850-4FD0-B46D-2B9F69081D57
D9: AuditId=84910_107393580_STD_76DC990E-8B41-474E-80E2-19FA65173E0D
D10: AuditId=96554_107393580_STD_4584CB4A-AD7A-40A7-936A-AF5C3F599EBE
D11: AuditId=109496_107393580_STD_6C5750DE-DE26-45FE-B414-E983390575C6
D12: AuditId=119080_107393580_STD_8188729F-1D90-4755-A9D9-80055338A825
D13: AuditId=128577_107393580_STD_CBF8EFB9-56F4-444B-B436-B0CD02DCA05A
D14: AuditId=138146_107393580_STD_6B491C50-4574-46A5-AAB6-631899E467AB
... D4137: AuditId=2155_117098222_STD_B19BFE22-CAD3-466D-A384-948696FCA09A

Sheet Sheet23
A1: =_xll.RDP.Data(Sheet1!$A$2:$A$696,"TR.F.NetIncAfterTax","Period=FY0 Frq=FY SDate=#1 EDate=#2 CH=Fd RH=IN;periodenddate",B2,Sheet2!$A$1,Sheet2!$A$2) -> Updated at 14:40:03
D2: Net Income after Tax
B3: CHP.HM | C3: 43830 | D3: 216054818493
B4: CHP.HM | C4: 44196 | D4: 278372060882
B5: CHP.HM | C5: 44561 | D5: 242074622322
B6: CHP.HM | C6: 44926 | D6: 510295093778
B7: CHP.HM | C7: 45291 | D7: 336954868099
B8: CHP.HM | C8: 45657 | D8: 313767090621
B9: V21.HN | C9: 43830 | D9: 661264024
B10: V21.HN | C10: 44196 | D10: 1150350656
B11: V21.HN | C11: 44561 | D11: 3713924322
B12: V21.HN | C12: 44926 | D12: 928884788
B13: V21.HN | C13: 45291 | D13: 59007958
B14: V21.HN | C14: 45657 | D14: -1176066225
... B592: JVC.HM | C592: 44286 | D592: -76685819426
B593: JVC.HM | C593: 44926 | D593: NULL
B594: JVC.HM | C594: 44926 | D594: NULL
B595: JVC.HM | C595: 45291 | D595: 52639842397
B596: JVC.HM | C596: 45657 | D596: 40336096061
B597: PTB.HM | C597: 43830 | D597: 456802969520
B598: PTB.HM | C598: 44196 | D598: 379305449080
B599: PTB.HM | C599: 44561 | D599: 525894613782
B600: PTB.HM | C600: 44926 | D600: 502438563190
B601: PTB.HM | C601: 45291 | D601: 259467307655
B602: PTB.HM | C602: 45657 | D602: 376311422056
B603: CIG.HM | C603: 43830 | D603: 125278920
B604: CIG.HM | C604: 44196 | D604: -174896569573
B605: CIG.HM | C605: 44561 | D605: 16548612398
B606: CIG.HM | C606: 44926 | D606: -6656969478
... B1685: ICT.HM | C1685: 45657 | D1685: 31104257416
B1686: NO1.HM | D1686: Unable to collect data for the field 'TR.F.NetIncAfterTax' and some specific identifier(s).
B1687: PCH.HN | C1687: 43830 | D1687: 6184561318
B1688: PCH.HN | C1688: 44196 | D1688: 12003756395
B1689: PCH.HN | C1689: 44561 | D1689: 12551310756
B1690: PCH.HN | C1690: 44926 | D1690: 14183284394
B1691: PCH.HN | C1691: 45291 | D1691: 12297857776
B1692: PCH.HN | C1692: 45657 | D1692: 12857134636
B1693: DVM.HN | C1693: 44196 | D1693: 21523631183
B1694: DVM.HN | C1694: 44561 | D1694: 50140891761
B1695: DVM.HN | C1695: 44926 | D1695: 54415230945
B1696: DVM.HN | C1696: 45291 | D1696: 43162348835
B1697: DVM.HN | C1697: 45657 | D1697: 47874884656
B1698: CAR.HN | C1698: 45291 | D1698: 3592531779
... B1763: DXS.HM | C1763: 45657 | D1763: 248079309374
B1764: CST.HN | C1764: 44196 | D1764: NULL
B1765: CST.HN | C1765: 44561 | D1765: 107131659618
B1766: CST.HN | C1766: 44926 | D1766: 358298643432
B1767: CST.HN | C1767: 45291 | D1767: 287924421824
B1768: CST.HN | C1768: 45657 | D1768: 130019867238
B1769: SCG.HN | C1769: 43830 | D1769: NULL
B1770: SCG.HN | C1770: 44196 | D1770: 90174956193
B1771: SCG.HN | C1771: 44561 | D1771: 151595933494
B1772: SCG.HN | C1772: 44926 | D1772: 35745015924
B1773: SCG.HN | C1773: 45291 | D1773: 21113528953
B1774: SCG.HN | C1774: 45657 | D1774: 198322921141
B1775: AAT.HM | C1775: 43830 | D1775: 21147090794
B1776: AAT.HM | C1776: 44196 | D1776: 14038467792
B1777: AAT.HM | C1777: 44561 | D1777: 28027696806
B1778: AAT.HM | C1778: 44926 | D1778: 67633771286
B1779: AAT.HM | C1779: 45291 | D1779: -2466576299
B1780: AAT.HM | C1780: 45657 | D1780: -8311081313
B1781: SSB.HM | C1781: 43830 | D1781: 1098452000000
... B2890: DPM.HM | C2890: 45657 | D2890: 554266541498
B2891: VPL.HM | C2891: 43830 | D2891: NULL
B2892: VPL.HM | C2892: 44196 | D2892: NULL
B2893: VPL.HM | C2893: 44561 | D2893: NULL
B2894: VPL.HM | C2894: 44926 | D2894: NULL
B2895: VPL.HM | C2895: 45291 | D2895: 670623000000
B2896: DQC.HM | C2896: 43830 | D2896: 29560680138
B2897: DQC.HM | C2897: 44196 | D2897: 18263877529
B2898: DQC.HM | C2898: 44561 | D2898: 22758693457
B2899: DQC.HM | C2899: 44926 | D2899: 14854693040
B2900: DQC.HM | C2900: 45291 | D2900: -33414291885
B2901: DQC.HM | C2901: 45657 | D2901: -121906476648
B2902: PIT.HM | C2902: 43830 | D2902: 6698001634
B2903: PIT.HM | C2903: 44196 | D2903: 1851284037
B2904: PIT.HM | C2904: 44561 | D2904: -5673007687
B2905: PIT.HM | C2905: 44926 | D2905: 3167717683
B2906: PIT.HM | C2906: 45291 | D2906: -8951107257
... B3941: CTD.HM | C3941: 44926 | D3941: 20791833411
B3942: CTD.HM | C3942: 45107 | D3942: NULL
B3943: CTD.HM | C3943: 45473 | D3943: 309592561393
B3944: CTD.HM | C3944: 45838 | D3944: 456211888815
B3945: ASM.HM | C3945: 43830 | D3945: 823347506552
B3946: ASM.HM | C3946: 44196 | D3946: 572357267708
B3947: ASM.HM | C3947: 44561 | D3947: 703887618610
B3948: ASM.HM | C3948: 44926 | D3948: 962584745306
B3949: ASM.HM | C3949: 45291 | D3949: 251699371212
B3950: ASM.HM | C3950: 45657 | D3950: 250986638049
B3951: LHC.HN | C3951: 43830 | D3951: 78047744510
B3952: LHC.HN | C3952: 44196 | D3952: 90687996238
B3953: LHC.HN | C3953: 44561 | D3953: 89264822936
B3954: LHC.HN | C3954: 44926 | D3954: 116800486967
... B4137: RYG.HM | C4137: 45657 | D4137: 67532124160
B4138: TCX.HM | D4138: Unable to collect data for the field 'TR.F.NetIncAfterTax' and some specific identifier(s).

Sheet ZjUxOWE2N2ItNTRjYi00Nm
D3: AuditId=84059_107403491_STD_9BF32382-3105-42E3-862E-9A4D9DE0A102
D4: AuditId=82676_107403491_STD_9B7E228C-30CC-47A9-BF23-D89134DA4202
D5: AuditId=59561400_107403491_STD_B94F5566-D734-4E4D-B3F0-2114155A5E1C
D6: AuditId=59562385_107403491_STD_B94F5566-D734-4E4D-B3F0-2114155A5E1C
D7: AuditId=192616531_107403491_STD_6C81D584-74D2-4A8C-8F9B-51699DB4BAA3
D8: AuditId=192615183_107403491_STD_E565C324-8850-4FD0-B46D-2B9F69081D57
D9: AuditId=84894_107393580_STD_76DC990E-8B41-474E-80E2-19FA65173E0D
D10: AuditId=96543_107393580_STD_4584CB4A-AD7A-40A7-936A-AF5C3F599EBE
D11: AuditId=109476_107393580_STD_6C5750DE-DE26-45FE-B414-E983390575C6
D12: AuditId=119061_107393580_STD_8188729F-1D90-4755-A9D9-80055338A825
D13: AuditId=128562_107393580_STD_CBF8EFB9-56F4-444B-B436-B0CD02DCA05A
D14: AuditId=138130_107393580_STD_6B491C50-4574-46A5-AAB6-631899E467AB
... D4137: AuditId=2135_117098222_STD_B19BFE22-CAD3-466D-A384-948696FCA09A

Sheet Sheet25
A1: =_xll.RDP.Data(Sheet1!$A$2:$A$696,"TR.F.TotRevenue","Period=FY0 Frq=FY SDate=#1 EDate=#2 CH=Fd RH=IN;periodenddate",B2,Sheet2!$A$1,Sheet2!$A$2) -> Updated at 14:44:32
D2: Revenue from Business Activities - Total
B3: CHP.HM | C3: 43830 | D3: 713535772923
B4: CHP.HM | C4: 44196 | D4: 830524857602
B5: CHP.HM | C5: 44561 | D5: 787447457857
B6: CHP.HM | C6: 44926 | D6: 1100534048069
B7: CHP.HM | C7: 45291 | D7: 881377927945
B8: CHP.HM | C8: 45657 | D8: 814199531520
B9: V21.HN | C9: 43830 | D9: 378114031343
B10: V21.HN | C10: 44196 | D10: 162752725227
B11: V21.HN | C11: 44561 | D11: 125499975935
B12: V21.HN | C12: 44926 | D12: 61220235368
B13: V21.HN | C13: 45291 | D13: 107609657162
B14: V21.HN | C14: 45657 | D14: 119230524183
... B592: JVC.HM | C592: 44286 | D592: 411416951706
B593: JVC.HM | C593: 44926 | D593: NULL
B594: JVC.HM | C594: 44926 | D594: NULL
B595: JVC.HM | C595: 45291 | D595: 576287155805
B596: JVC.HM | C596: 45657 | D596: 611540459301
B597: PTB.HM | C597: 43830 | D597: 5549137355104
B598: PTB.HM | C598: 44196 | D598: 5601236769697
B599: PTB.HM | C599: 44561 | D599: 6491949040731
B600: PTB.HM | C600: 44926 | D600: 6886522253734
B601: PTB.HM | C601: 45291 | D601: 5618569890239
B602: PTB.HM | C602: 45657 | D602: 6466470034276
B603: CIG.HM | C603: 43830 | D603: 2589213336
B604: CIG.HM | C604: 44196 | D604: 25610385676
B605: CIG.HM | C605: 44561 | D605: 29583834844
B606: CIG.HM | C606: 44926 | D606: 83224739215
... B1685: ICT.HM | C1685: 45657 | D1685: 1572511299308
B1686: NO1.HM | D1686: Unable to collect data for the field 'TR.F.TotRevenue' and some specific identifier(s).
B1687: PCH.HN | C1687: 43830 | D1687: 115018059644
B1688: PCH.HN | C1688: 44196 | D1688: 128910028821
B1689: PCH.HN | C1689: 44561 | D1689: 125604903978
B1690: PCH.HN | C1690: 44926 | D1690: 151962809609
B1691: PCH.HN | C1691: 45291 | D1691: 124650435594
B1692: PCH.HN | C1692: 45657 | D1692: 194942239067
B1693: DVM.HN | C1693: 44196 | D1693: 842716225965
B1694: DVM.HN | C1694: 44561 | D1694: 1048919705587
B1695: DVM.HN | C1695: 44926 | D1695: 1178951172555
B1696: DVM.HN | C1696: 45291 | D1696: 1481719683532
B1697: DVM.HN | C1697: 45657 | D1697: 1579969259142
B1698: CAR.HN | C1698: 45291 | D1698: 81016604570
... B1763: DXS.HM | C1763: 45657 | D1763: 2437886746721
B1764: CST.HN | C1764: 44196 | D1764: NULL
B1765: CST.HN | C1765: 44561 | D1765: 8701894493965
B1766: CST.HN | C1766: 44926 | D1766: 10388800088907
B1767: CST.HN | C1767: 45291 | D1767: 7905709420622
B1768: CST.HN | C1768: 45657 | D1768: 9448093858111
B1769: SCG.HN | C1769: 43830 | D1769: NULL
B1770: SCG.HN | C1770: 44196 | D1770: 1420345755182
B1771: SCG.HN | C1771: 44561 | D1771: 2857279789954
B1772: SCG.HN | C1772: 44926 | D1772: 1742069035322
B1773: SCG.HN | C1773: 45291 | D1773: 793597911306
B1774: SCG.HN | C1774: 45657 | D1774: 2705064519164
B1775: AAT.HM | C1775: 43830 | D1775: 296395817053
B1776: AAT.HM | C1776: 44196 | D1776: 287098931865
B1777: AAT.HM | C1777: 44561 | D1777: 473174997084
B1778: AAT.HM | C1778: 44926 | D1778: 961625809112
B1779: AAT.HM | C1779: 45291 | D1779: 599354540320
B1780: AAT.HM | C1780: 45657 | D1780: 583009927395
B1781: SSB.HM | C1781: 43830 | D1781: 3646482000000
... B2890: DPM.HM | C2890: 45657 | D2890: 13496142223703
B2891: VPL.HM | C2891: 43830 | D2891: NULL
B2892: VPL.HM | C2892: 44196 | D2892: NULL
B2893: VPL.HM | C2893: 44561 | D2893: NULL
B2894: VPL.HM | C2894: 44926 | D2894: NULL
B2895: VPL.HM | C2895: 45291 | D2895: 9254103000000
B2896: DQC.HM | C2896: 43830 | D2896: 824909982398
B2897: DQC.HM | C2897: 44196 | D2897: 940221687831
B2898: DQC.HM | C2898: 44561 | D2898: 733831365162
B2899: DQC.HM | C2899: 44926 | D2899: 989644661618
B2900: DQC.HM | C2900: 45291 | D2900: 859018218251
B2901: DQC.HM | C2901: 45657 | D2901: 813628032087
B2902: PIT.HM | C2902: 43830 | D2902: 911883953662
B2903: PIT.HM | C2903: 44196 | D2903: 551101153385
B2904: PIT.HM | C2904: 44561 | D2904: 873245853229
B2905: PIT.HM | C2905: 44926 | D2905: 791750875340
B2906: PIT.HM | C2906: 45291 | D2906: 708653549026
... B3941: CTD.HM | C3941: 44926 | D3941: 14536948503110
B3942: CTD.HM | C3942: 45107 | D3942: NULL
B3943: CTD.HM | C3943: 45473 | D3943: 21045158770378
B3944: CTD.HM | C3944: 45838 | D3944: 24884531092428
B3945: ASM.HM | C3945: 43830 | D3945: 14223773341105
B3946: ASM.HM | C3946: 44196 | D3946: 12524613811857
B3947: ASM.HM | C3947: 44561 | D3947: 11397925912454
B3948: ASM.HM | C3948: 44926 | D3948: 13749221971690
B3949: ASM.HM | C3949: 45291 | D3949: 11973153752107
B3950: ASM.HM | C3950: 45657 | D3950: 12013117890000
B3951: LHC.HN | C3951: 43830 | D3951: 757567636124
B3952: LHC.HN | C3952: 44196 | D3952: 866888005671
B3953: LHC.HN | C3953: 44561 | D3953: 1054939540593
B3954: LHC.HN | C3954: 44926 | D3954: 1416508809812
... B4137: RYG.HM | C4137: 45657 | D4137: 1692068298627
B4138: TCX.HM | D4138: Unable to collect data for the field 'TR.F.TotRevenue' and some specific identifier(s).

Sheet Sheet27
A1: =_xll.RDP.Data(Sheet1!$A$2:$A$696,"TR.F.IncBefTax","Period=FY0 Frq=FY SDate=#1 EDate=#2 CH=Fd RH=IN;periodenddate",B2,Sheet2!$A$1,Sheet2!$A$2) -> Updated at 14:45:53
D2: Income before Taxes
B3: CHP.HM | C3: 43830 | D3: 226713780181
B4: CHP.HM | C4: 44196 | D4: 290832743157
B5: CHP.HM | C5: 44561 | D5: 254492336625
B6: CHP.HM | C6: 44926 | D6: 535957349060
B7: CHP.HM | C7: 45291 | D7: 355431626080
B8: CHP.HM | C8: 45657 | D8: 331962474374
B9: V21.HN | C9: 43830 | D9: 2377163766
B10: V21.HN | C10: 44196 | D10: 1590539789
B11: V21.HN | C11: 44561 | D11: 3713924322
B12: V21.HN | C12: 44926 | D12: 928884788
B13: V21.HN | C13: 45291 | D13: 402036526
B14: V21.HN | C14: 45657 | D14: -1176066225
... B592: JVC.HM | C592: 44286 | D592: -76578967464
B593: JVC.HM | C593: 44926 | D593: NULL
B594: JVC.HM | C594: 44926 | D594: NULL
B595: JVC.HM | C595: 45291 | D595: 55924271928
B596: JVC.HM | C596: 45657 | D596: 58865008889
B597: PTB.HM | C597: 43830 | D597: 550035460492
B598: PTB.HM | C598: 44196 | D598: 462307957661
B599: PTB.HM | C599: 44561 | D599: 650493184310
B600: PTB.HM | C600: 44926 | D600: 613995640567
B601: PTB.HM | C601: 45291 | D601: 322753317301
B602: PTB.HM | C602: 45657 | D602: 471981832117
B603: CIG.HM | C603: 43830 | D603: 1208542024
B604: CIG.HM | C604: 44196 | D604: -174896569573
B605: CIG.HM | C605: 44561 | D605: 16552136016
B606: CIG.HM | C606: 44926 | D606: -6631291648
... B1685: ICT.HM | C1685: 45657 | D1685: 37182705522
B1686: NO1.HM | D1686: Unable to collect data for the field 'TR.F.IncBefTax' and some specific identifier(s).
B1687: PCH.HN | C1687: 43830 | D1687: 7743372206
B1688: PCH.HN | C1688: 44196 | D1688: 14317878476
B1689: PCH.HN | C1689: 44561 | D1689: 14957263959
B1690: PCH.HN | C1690: 44926 | D1690: 18103971424
B1691: PCH.HN | C1691: 45291 | D1691: 15033082796
B1692: PCH.HN | C1692: 45657 | D1692: 17314275712
B1693: DVM.HN | C1693: 44196 | D1693: 24338397450
B1694: DVM.HN | C1694: 44561 | D1694: 54446873583
B1695: DVM.HN | C1695: 44926 | D1695: 63703061248
B1696: DVM.HN | C1696: 45291 | D1696: 49496268227
B1697: DVM.HN | C1697: 45657 | D1697: 55401459321
B1698: CAR.HN | C1698: 45291 | D1698: 4593661183
... B1763: DXS.HM | C1763: 45657 | D1763: 341332292978
B1764: CST.HN | C1764: 44196 | D1764: NULL
B1765: CST.HN | C1765: 44561 | D1765: 135927103109
B1766: CST.HN | C1766: 44926 | D1766: 448558607289
B1767: CST.HN | C1767: 45291 | D1767: 361040726769
B1768: CST.HN | C1768: 45657 | D1768: 163002807504
B1769: SCG.HN | C1769: 43830 | D1769: NULL
B1770: SCG.HN | C1770: 44196 | D1770: 112740214938
B1771: SCG.HN | C1771: 44561 | D1771: 203640121711
B1772: SCG.HN | C1772: 44926 | D1772: 78965214702
B1773: SCG.HN | C1773: 45291 | D1773: 24666539055
B1774: SCG.HN | C1774: 45657 | D1774: 227713700461
B1775: AAT.HM | C1775: 43830 | D1775: 25932376638
B1776: AAT.HM | C1776: 44196 | D1776: 18630112181
B1777: AAT.HM | C1777: 44561 | D1777: 35716121781
B1778: AAT.HM | C1778: 44926 | D1778: 90734156999
B1779: AAT.HM | C1779: 45291 | D1779: -330961397
B1780: AAT.HM | C1780: 45657 | D1780: -4879100934
B1781: SSB.HM | C1781: 43830 | D1781: 1390698000000
... B2890: DPM.HM | C2890: 45657 | D2890: 669331577098
B2891: VPL.HM | C2891: 43830 | D2891: NULL
B2892: VPL.HM | C2892: 44196 | D2892: NULL
B2893: VPL.HM | C2893: 44561 | D2893: NULL
B2894: VPL.HM | C2894: 44926 | D2894: NULL
B2895: VPL.HM | C2895: 45291 | D2895: 766310000000
B2896: DQC.HM | C2896: 43830 | D2896: 36905164137
B2897: DQC.HM | C2897: 44196 | D2897: 22424687251
B2898: DQC.HM | C2898: 44561 | D2898: 24798582675
B2899: DQC.HM | C2899: 44926 | D2899: 15751321545
B2900: DQC.HM | C2900: 45291 | D2900: -30621738873
B2901: DQC.HM | C2901: 45657 | D2901: -120834463962
B2902: PIT.HM | C2902: 43830 | D2902: 11473735029
B2903: PIT.HM | C2903: 44196 | D2903: 1854718440
B2904: PIT.HM | C2904: 44561 | D2904: -5593275557
B2905: PIT.HM | C2905: 44926 | D2905: 3819465786
B2906: PIT.HM | C2906: 45291 | D2906: -8929440591
... B3941: CTD.HM | C3941: 44926 | D3941: 34825553879
B3942: CTD.HM | C3942: 45107 | D3942: NULL
B3943: CTD.HM | C3943: 45473 | D3943: 386562030631
B3944: CTD.HM | C3944: 45838 | D3944: 552011164947
B3945: ASM.HM | C3945: 43830 | D3945: 871739467430
B3946: ASM.HM | C3946: 44196 | D3946: 624305442889
B3947: ASM.HM | C3947: 44561 | D3947: 786296291797
B3948: ASM.HM | C3948: 44926 | D3948: 1061984130515
B3949: ASM.HM | C3949: 45291 | D3949: 319141424156
B3950: ASM.HM | C3950: 45657 | D3950: 317093997015
B3951: LHC.HN | C3951: 43830 | D3951: 98892838442
B3952: LHC.HN | C3952: 44196 | D3952: 110649244591
B3953: LHC.HN | C3953: 44561 | D3953: 109619275126
B3954: LHC.HN | C3954: 44926 | D3954: 147992999919
... B4137: RYG.HM | C4137: 45657 | D4137: 83819457415
B4138: TCX.HM | D4138: Unable to collect data for the field 'TR.F.IncBefTax' and some specific identifier(s).

Sheet MThkOGYxZGEtYzk1ZC00MT
D3: AuditId=84072_107403491_STD_9BF32382-3105-42E3-862E-9A4D9DE0A102
D4: AuditId=82686_107403491_STD_9B7E228C-30CC-47A9-BF23-D89134DA4202
D5: AuditId=59561413_107403491_STD_B94F5566-D734-4E4D-B3F0-2114155A5E1C
D6: AuditId=59562399_107403491_STD_B94F5566-D734-4E4D-B3F0-2114155A5E1C
D7: AuditId=192616543_107403491_STD_6C81D584-74D2-4A8C-8F9B-51699DB4BAA3
D8: AuditId=192615193_107403491_STD_E565C324-8850-4FD0-B46D-2B9F69081D57
D9: AuditId=84906_107393580_STD_76DC990E-8B41-474E-80E2-19FA65173E0D
D10: AuditId=96553_107393580_STD_4584CB4A-AD7A-40A7-936A-AF5C3F599EBE
D11: AuditId=109489_107393580_STD_6C5750DE-DE26-45FE-B414-E983390575C6
D12: AuditId=119075_107393580_STD_8188729F-1D90-4755-A9D9-80055338A825
D13: AuditId=128572_107393580_STD_CBF8EFB9-56F4-444B-B436-B0CD02DCA05A
D14: AuditId=138141_107393580_STD_6B491C50-4574-46A5-AAB6-631899E467AB
... D4137: AuditId=2148_117098222_STD_B19BFE22-CAD3-466D-A384-948696FCA09A

Sheet ZjM4ZmM2NmMtNDY1ZS00ZT
D3: AuditId=84075_107403491_STD_9BF32382-3105-42E3-862E-9A4D9DE0A102
D4: AuditId=82689_107403491_STD_9B7E228C-30CC-47A9-BF23-D89134DA4202
D5: AuditId=59561420_107403491_STD_B94F5566-D734-4E4D-B3F0-2114155A5E1C
D6: AuditId=59562402_107403491_STD_B94F5566-D734-4E4D-B3F0-2114155A5E1C
D7: AuditId=192616546_107403491_STD_6C81D584-74D2-4A8C-8F9B-51699DB4BAA3
D8: AuditId=192615196_107403491_STD_E565C324-8850-4FD0-B46D-2B9F69081D57
D9: AuditId=84910_107393580_STD_76DC990E-8B41-474E-80E2-19FA65173E0D
D10: AuditId=96554_107393580_STD_4584CB4A-AD7A-40A7-936A-AF5C3F599EBE
D11: AuditId=109496_107393580_STD_6C5750DE-DE26-45FE-B414-E983390575C6
D12: AuditId=119080_107393580_STD_8188729F-1D90-4755-A9D9-80055338A825
D13: AuditId=128577_107393580_STD_CBF8EFB9-56F4-444B-B436-B0CD02DCA05A
D14: AuditId=138146_107393580_STD_6B491C50-4574-46A5-AAB6-631899E467AB
... D4137: AuditId=2155_117098222_STD_B19BFE22-CAD3-466D-A384-948696FCA09A

Sheet YmFlYWM4NmItZDc4NS00ZT
D3: AuditId=83979_107403491_STD_9BF32382-3105-42E3-862E-9A4D9DE0A102
D4: AuditId=82622_107403491_STD_9B7E228C-30CC-47A9-BF23-D89134DA4202
D5: AuditId=59561293_107403491_STD_B94F5566-D734-4E4D-B3F0-2114155A5E1C
D6: AuditId=59562312_107403491_STD_B94F5566-D734-4E4D-B3F0-2114155A5E1C
D7: AuditId=192616459_107403491_STD_6C81D584-74D2-4A8C-8F9B-51699DB4BAA3
D8: AuditId=192615130_107403491_STD_E565C324-8850-4FD0-B46D-2B9F69081D57
D10: AuditId=87388_107345512_STD_7B8F1745-6942-46B4-BA25-8101F8D58C43
D11: AuditId=100576_107345512_STD_10E5FD24-B4A6-466A-8B7F-8FDBDD7A2CDA
D12: AuditId=115496_107345512_STD_5765C885-696A-4BB0-8345-B5D1C83BDED9
D13: AuditId=126248_107345512_STD_C5C6F882-0625-4D02-8D51-B637A286169C
D14: AuditId=149931_107345512_STD_108A8818-44A6-46C9-8EEB-4DFE5ED8CAE2
D15: AuditId=148453_107345512_STD_740CA875-3E53-498F-B93C-9A2072BC6A88
... D3248: AuditId=2063_117098222_STD_B19BFE22-CAD3-466D-A384-948696FCA09A

Sheet Sheet28
A1: =_xll.RDP.Data(Sheet1!$A$2:$A$696,"TR.F.NetIncAfterTax","Period=FY0 Frq=FY SDate=#1 EDate=#2 CH=Fd RH=IN;periodenddate",B2,Sheet2!$A$1,Sheet2!$A$2) -> Updated at 14:49:16
D2: Net Income after Tax
B3: CHP.HM | C3: 43830 | D3: 216054818493
B4: CHP.HM | C4: 44196 | D4: 278372060882
B5: CHP.HM | C5: 44561 | D5: 242074622322
B6: CHP.HM | C6: 44926 | D6: 510295093778
B7: CHP.HM | C7: 45291 | D7: 336954868099
B8: CHP.HM | C8: 45657 | D8: 313767090621
B9: V21.HN | C9: 43830 | D9: 661264024
B10: V21.HN | C10: 44196 | D10: 1150350656
B11: V21.HN | C11: 44561 | D11: 3713924322
B12: V21.HN | C12: 44926 | D12: 928884788
B13: V21.HN | C13: 45291 | D13: 59007958
B14: V21.HN | C14: 45657 | D14: -1176066225
... B592: JVC.HM | C592: 44286 | D592: -76685819426
B593: JVC.HM | C593: 44926 | D593: NULL
B594: JVC.HM | C594: 44926 | D594: NULL
B595: JVC.HM | C595: 45291 | D595: 52639842397
B596: JVC.HM | C596: 45657 | D596: 40336096061
B597: PTB.HM | C597: 43830 | D597: 456802969520
B598: PTB.HM | C598: 44196 | D598: 379305449080
B599: PTB.HM | C599: 44561 | D599: 525894613782
B600: PTB.HM | C600: 44926 | D600: 502438563190
B601: PTB.HM | C601: 45291 | D601: 259467307655
B602: PTB.HM | C602: 45657 | D602: 376311422056
B603: CIG.HM | C603: 43830 | D603: 125278920
B604: CIG.HM | C604: 44196 | D604: -174896569573
B605: CIG.HM | C605: 44561 | D605: 16548612398
B606: CIG.HM | C606: 44926 | D606: -6656969478
... B1685: ICT.HM | C1685: 45657 | D1685: 31104257416
B1686: NO1.HM | D1686: Unable to collect data for the field 'TR.F.NetIncAfterTax' and some specific identifier(s).
B1687: PCH.HN | C1687: 43830 | D1687: 6184561318
B1688: PCH.HN | C1688: 44196 | D1688: 12003756395
B1689: PCH.HN | C1689: 44561 | D1689: 12551310756
B1690: PCH.HN | C1690: 44926 | D1690: 14183284394
B1691: PCH.HN | C1691: 45291 | D1691: 12297857776
B1692: PCH.HN | C1692: 45657 | D1692: 12857134636
B1693: DVM.HN | C1693: 44196 | D1693: 21523631183
B1694: DVM.HN | C1694: 44561 | D1694: 50140891761
B1695: DVM.HN | C1695: 44926 | D1695: 54415230945
B1696: DVM.HN | C1696: 45291 | D1696: 43162348835
B1697: DVM.HN | C1697: 45657 | D1697: 47874884656
B1698: CAR.HN | C1698: 45291 | D1698: 3592531779
... B1763: DXS.HM | C1763: 45657 | D1763: 248079309374
B1764: CST.HN | C1764: 44196 | D1764: NULL
B1765: CST.HN | C1765: 44561 | D1765: 107131659618
B1766: CST.HN | C1766: 44926 | D1766: 358298643432
B1767: CST.HN | C1767: 45291 | D1767: 287924421824
B1768: CST.HN | C1768: 45657 | D1768: 130019867238
B1769: SCG.HN | C1769: 43830 | D1769: NULL
B1770: SCG.HN | C1770: 44196 | D1770: 90174956193
B1771: SCG.HN | C1771: 44561 | D1771: 151595933494
B1772: SCG.HN | C1772: 44926 | D1772: 35745015924
B1773: SCG.HN | C1773: 45291 | D1773: 21113528953
B1774: SCG.HN | C1774: 45657 | D1774: 198322921141
B1775: AAT.HM | C1775: 43830 | D1775: 21147090794
B1776: AAT.HM | C1776: 44196 | D1776: 14038467792
B1777: AAT.HM | C1777: 44561 | D1777: 28027696806
B1778: AAT.HM | C1778: 44926 | D1778: 67633771286
B1779: AAT.HM | C1779: 45291 | D1779: -2466576299
B1780: AAT.HM | C1780: 45657 | D1780: -8311081313
B1781: SSB.HM | C1781: 43830 | D1781: 1098452000000
... B2890: DPM.HM | C2890: 45657 | D2890: 554266541498
B2891: VPL.HM | C2891: 43830 | D2891: NULL
B2892: VPL.HM | C2892: 44196 | D2892: NULL
B2893: VPL.HM | C2893: 44561 | D2893: NULL
B2894: VPL.HM | C2894: 44926 | D2894: NULL
B2895: VPL.HM | C2895: 45291 | D2895: 670623000000
B2896: DQC.HM | C2896: 43830 | D2896: 29560680138
B2897: DQC.HM | C2897: 44196 | D2897: 18263877529
B2898: DQC.HM | C2898: 44561 | D2898: 22758693457
B2899: DQC.HM | C2899: 44926 | D2899: 14854693040
B2900: DQC.HM | C2900: 45291 | D2900: -33414291885
B2901: DQC.HM | C2901: 45657 | D2901: -121906476648
B2902: PIT.HM | C2902: 43830 | D2902: 6698001634
B2903: PIT.HM | C2903: 44196 | D2903: 1851284037
B2904: PIT.HM | C2904: 44561 | D2904: -5673007687
B2905: PIT.HM | C2905: 44926 | D2905: 3167717683
B2906: PIT.HM | C2906: 45291 | D2906: -8951107257
... B3941: CTD.HM | C3941: 44926 | D3941: 20791833411
B3942: CTD.HM | C3942: 45107 | D3942: NULL
B3943: CTD.HM | C3943: 45473 | D3943: 309592561393
B3944: CTD.HM | C3944: 45838 | D3944: 456211888815
B3945: ASM.HM | C3945: 43830 | D3945: 823347506552
B3946: ASM.HM | C3946: 44196 | D3946: 572357267708
B3947: ASM.HM | C3947: 44561 | D3947: 703887618610
B3948: ASM.HM | C3948: 44926 | D3948: 962584745306
B3949: ASM.HM | C3949: 45291 | D3949: 251699371212
B3950: ASM.HM | C3950: 45657 | D3950: 250986638049
B3951: LHC.HN | C3951: 43830 | D3951: 78047744510
B3952: LHC.HN | C3952: 44196 | D3952: 90687996238
B3953: LHC.HN | C3953: 44561 | D3953: 89264822936
B3954: LHC.HN | C3954: 44926 | D3954: 116800486967
... B4137: RYG.HM | C4137: 45657 | D4137: 67532124160
B4138: TCX.HM | D4138: Unable to collect data for the field 'TR.F.NetIncAfterTax' and some specific identifier(s).

Sheet Sheet31
A1: =_xll.RDP.Data(Sheet1!$A$2:$A$696,"TR.F.GrossTotRevBizActiv","Period=FY0 Frq=FY SDate=#1 EDate=#2 CH=Fd RH=IN;periodenddate",B2,Sheet2!$A$1,Sheet2!$A$2) -> Updated at 14:47:58
D2: Gross Revenue from Business Activities - Total
B3: CHP.HM | C3: 43830 | D3: 713535772923
B4: CHP.HM | C4: 44196 | D4: 830524857602
B5: CHP.HM | C5: 44561 | D5: 787447457857
B6: CHP.HM | C6: 44926 | D6: 1100534048069
B7: CHP.HM | C7: 45291 | D7: 881377927945
B8: CHP.HM | C8: 45657 | D8: 814199531520
B9: V21.HN | D9: NULL
B10: LIG.HN | C10: 43830 | D10: 2228795106735
B11: LIG.HN | C11: 44196 | D11: 2341590275188
B12: LIG.HN | C12: 44561 | D12: 2439778222621
B13: LIG.HN | C13: 44926 | D13: 2968797065446
B14: LIG.HN | C14: 45291 | D14: 3325201927581
B15: LIG.HN | C15: 45657 | D15: 3695151811446
B16: MCC.HN | D16: NULL
B17: TET.HN | C17: 43830 | D17: 24854514818
B18: TET.HN | C18: 44196 | D18: 22682602637
B19: TET.HN | C19: 44561 | D19: 22593129147
B20: TET.HN | C20: 44926 | D20: 22997604620
B21: TET.HN | C21: 45291 | D21: 23988586386
B22: TET.HN | C22: 45657 | D22: 23541850564
B23: KSD.HN | C23: 43830 | D23: 105196797937
B24: KSD.HN | C24: 44196 | D24: 12162171254
B25: KSD.HN | C25: 44561 | D25: 68826576091
B26: KSD.HN | C26: 44926 | D26: 102955130039
B27: KSD.HN | C27: 45291 | D27: 52357797331
B28: KSD.HN | C28: 45657 | D28: 47136727334
... B58: NVT.HM | C58: 45657 | D58: 410702451708
B59: VCM.HN | D59: NULL
B60: SPM.HM | C60: 43830 | D60: 555755824664
B61: SPM.HM | C61: 44196 | D61: 660069034058
B62: SPM.HM | C62: 44561 | D62: 768359616822
B63: SPM.HM | C63: 44926 | D63: 771276505025
B64: SPM.HM | C64: 45291 | D64: 461031858201
B65: SPM.HM | C65: 45657 | D65: 348984734523
B66: CX8.HN | D66: NULL
B67: TNT.HM | C67: 43830 | D67: 176314537729
B68: TNT.HM | C68: 44196 | D68: 12866920534
B69: TNT.HM | C69: 44561 | D69: 640949396541
B70: TNT.HM | C70: 44926 | D70: 379278024325
B71: TNT.HM | C71: 45291 | D71: 637508889656
B72: TNT.HM | C72: 45657 | D72: 918232190646
B73: HU1.HM | C73: 43830 | D73: 574987046336
B74: HU1.HM | C74: 44196 | D74: 397773143840
B75: HU1.HM | C75: 44561 | D75: 795594371484
B76: HU1.HM | C76: 44926 | D76: 481098393898
B77: HU1.HM | C77: 45291 | D77: 183849160657
B78: HU1.HM | C78: 45657 | D78: 233432704415
B79: SBA.HM | D79: NULL
B80: IDV.HN | D80: NULL
B81: AME.HN | C81: 43830 | D81: 1009257291364
B82: AME.HN | C82: 44196 | D82: 1410777561757
B83: AME.HN | C83: 44561 | D83: 1784702868306
B84: AME.HN | C84: 44926 | D84: 2213252011607
B85: AME.HN | C85: 45291 | D85: 2215317341019
B86: AME.HN | C86: 45657 | D86: 3371164038356
B87: DTL.HM | C87: 43830 | D87: 2517200392762
B88: DTL.HM | C88: 44196 | D88: 1983198923211
B89: DTL.HM | C89: 44561 | D89: 1381840902134
B90: DTL.HM | C90: 44926 | D90: 1613986903890
B91: DTL.HM | C91: 45291 | D91: 1972528403687
B92: DTL.HM | C92: 45657 | D92: 1966999544521
... B104: PDN.HM | C104: 45657 | D104: 1337315365298
B105: NNC.HM | D105: NULL
B106: DLG.HM | C106: 43830 | D106: 2873271991767
B107: DLG.HM | C107: 44196 | D107: 2039143865644
B108: DLG.HM | C108: 44561 | D108: 1549207937792
B109: DLG.HM | C109: 44926 | D109: 1347873447005
B110: DLG.HM | C110: 45291 | D110: 1122336737017
B111: DLG.HM | C111: 45657 | D111: 1058723073994
B112: CMV.HM | C112: 43830 | D112: 4728813920038
B113: CMV.HM | C113: 44196 | D113: 4222119804921
B114: CMV.HM | C114: 44561 | D114: 3861622463032
B115: CMV.HM | C115: 44926 | D115: 4524496458337
B116: CMV.HM | C116: 45291 | D116: 4260772905349
B117: CMV.HM | C117: 45657 | D117: 4609119646920
B118: VE3.HN | D118: NULL
B119: BCE.HM | C119: 43830 | D119: 633046316525
B120: BCE.HM | C120: 44196 | D120: 422702772553
B121: BCE.HM | C121: 44561 | D121: 111236733368
B122: BCE.HM | C122: 44926 | D122: 110553230706
B123: BCE.HM | C123: 45291 | D123: 100491989610
B124: BCE.HM | C124: 45657 | D124: 298034721682
B125: DC2.HN | D125: NULL
B126: ORS.HM | D126: NULL
B127: DTA.HM | C127: 43830 | D127: 54219846647
B128: DTA.HM | C128: 44196 | D128: 47445137871
B129: DTA.HM | C129: 44561 | D129: 108838675058
B130: DTA.HM | C130: 44926 | D130: 131158631689
B131: DTA.HM | C131: 45291 | D131: 100007683374
B132: DTA.HM | C132: 45657 | D132: 142968937296
B133: NHA.HM | D133: NULL
B134: AAA.HM | C134: 43830 | D134: 9278251727409
B135: AAA.HM | C135: 44196 | D135: 7438249657913
B136: AAA.HM | C136: 44561 | D136: 13154009928330
B137: AAA.HM | C137: 44926 | D137: 15314698238896
B138: AAA.HM | C138: 45291 | D138: 12628191473898
B139: AAA.HM | C139: 45657 | D139: 12787713250229
B140: HBS.HN | D140: NULL
...

Sheet MDBkNTA5MzMtODI4ZS00ND
D3: AuditId=84059_107403491_STD_9BF32382-3105-42E3-862E-9A4D9DE0A102
D4: AuditId=82676_107403491_STD_9B7E228C-30CC-47A9-BF23-D89134DA4202
D5: AuditId=59561400_107403491_STD_B94F5566-D734-4E4D-B3F0-2114155A5E1C
D6: AuditId=59562385_107403491_STD_B94F5566-D734-4E4D-B3F0-2114155A5E1C
D7: AuditId=192616531_107403491_STD_6C81D584-74D2-4A8C-8F9B-51699DB4BAA3
D8: AuditId=192615183_107403491_STD_E565C324-8850-4FD0-B46D-2B9F69081D57
D9: AuditId=84894_107393580_STD_76DC990E-8B41-474E-80E2-19FA65173E0D
D10: AuditId=96543_107393580_STD_4584CB4A-AD7A-40A7-936A-AF5C3F599EBE
D11: AuditId=109476_107393580_STD_6C5750DE-DE26-45FE-B414-E983390575C6
D12: AuditId=119061_107393580_STD_8188729F-1D90-4755-A9D9-80055338A825
D13: AuditId=128562_107393580_STD_CBF8EFB9-56F4-444B-B436-B0CD02DCA05A
D14: AuditId=138130_107393580_STD_6B491C50-4574-46A5-AAB6-631899E467AB
... D4137: AuditId=2135_117098222_STD_B19BFE22-CAD3-466D-A384-948696FCA09A

Sheet Sheet33
A1: =_xll.RDP.Data(Sheet1!$A$2:$A$696,"TR.F.TotRevenue","Period=FY0 Frq=FY SDate=#1 EDate=#2 CH=Fd RH=IN;periodenddate",B2,Sheet2!$A$1,Sheet2!$A$2) -> Updated at 14:49:47
D2: Revenue from Business Activities - Total
B3: CHP.HM | C3: 43830 | D3: 713535772923
B4: CHP.HM | C4: 44196 | D4: 830524857602
B5: CHP.HM | C5: 44561 | D5: 787447457857
B6: CHP.HM | C6: 44926 | D6: 1100534048069
B7: CHP.HM | C7: 45291 | D7: 881377927945
B8: CHP.HM | C8: 45657 | D8: 814199531520
B9: V21.HN | C9: 43830 | D9: 378114031343
B10: V21.HN | C10: 44196 | D10: 162752725227
B11: V21.HN | C11: 44561 | D11: 125499975935
B12: V21.HN | C12: 44926 | D12: 61220235368
B13: V21.HN | C13: 45291 | D13: 107609657162
B14: V21.HN | C14: 45657 | D14: 119230524183
... B592: JVC.HM | C592: 44286 | D592: 411416951706
B593: JVC.HM | C593: 44926 | D593: NULL
B594: JVC.HM | C594: 44926 | D594: NULL
B595: JVC.HM | C595: 45291 | D595: 576287155805
B596: JVC.HM | C596: 45657 | D596: 611540459301
B597: PTB.HM | C597: 43830 | D597: 5549137355104
B598: PTB.HM | C598: 44196 | D598: 5601236769697
B599: PTB.HM | C599: 44561 | D599: 6491949040731
B600: PTB.HM | C600: 44926 | D600: 6886522253734
B601: PTB.HM | C601: 45291 | D601: 5618569890239
B602: PTB.HM | C602: 45657 | D602: 6466470034276
B603: CIG.HM | C603: 43830 | D603: 2589213336
B604: CIG.HM | C604: 44196 | D604: 25610385676
B605: CIG.HM | C605: 44561 | D605: 29583834844
B606: CIG.HM | C606: 44926 | D606: 83224739215
... B1685: ICT.HM | C1685: 45657 | D1685: 1572511299308
B1686: NO1.HM | D1686: Unable to collect data for the field 'TR.F.TotRevenue' and some specific identifier(s).
B1687: PCH.HN | C1687: 43830 | D1687: 115018059644
B1688: PCH.HN | C1688: 44196 | D1688: 128910028821
B1689: PCH.HN | C1689: 44561 | D1689: 125604903978
B1690: PCH.HN | C1690: 44926 | D1690: 151962809609
B1691: PCH.HN | C1691: 45291 | D1691: 124650435594
B1692: PCH.HN | C1692: 45657 | D1692: 194942239067
B1693: DVM.HN | C1693: 44196 | D1693: 842716225965
B1694: DVM.HN | C1694: 44561 | D1694: 1048919705587
B1695: DVM.HN | C1695: 44926 | D1695: 1178951172555
B1696: DVM.HN | C1696: 45291 | D1696: 1481719683532
B1697: DVM.HN | C1697: 45657 | D1697: 1579969259142
B1698: CAR.HN | C1698: 45291 | D1698: 81016604570
... B1763: DXS.HM | C1763: 45657 | D1763: 2437886746721
B1764: CST.HN | C1764: 44196 | D1764: NULL
B1765: CST.HN | C1765: 44561 | D1765: 8701894493965
B1766: CST.HN | C1766: 44926 | D1766: 10388800088907
B1767: CST.HN | C1767: 45291 | D1767: 7905709420622
B1768: CST.HN | C1768: 45657 | D1768: 9448093858111
B1769: SCG.HN | C1769: 43830 | D1769: NULL
B1770: SCG.HN | C1770: 44196 | D1770: 1420345755182
B1771: SCG.HN | C1771: 44561 | D1771: 2857279789954
B1772: SCG.HN | C1772: 44926 | D1772: 1742069035322
B1773: SCG.HN | C1773: 45291 | D1773: 793597911306
B1774: SCG.HN | C1774: 45657 | D1774: 2705064519164
B1775: AAT.HM | C1775: 43830 | D1775: 296395817053
B1776: AAT.HM | C1776: 44196 | D1776: 287098931865
B1777: AAT.HM | C1777: 44561 | D1777: 473174997084
B1778: AAT.HM | C1778: 44926 | D1778: 961625809112
B1779: AAT.HM | C1779: 45291 | D1779: 599354540320
B1780: AAT.HM | C1780: 45657 | D1780: 583009927395
B1781: SSB.HM | C1781: 43830 | D1781: 3646482000000
... B2890: DPM.HM | C2890: 45657 | D2890: 13496142223703
B2891: VPL.HM | C2891: 43830 | D2891: NULL
B2892: VPL.HM | C2892: 44196 | D2892: NULL
B2893: VPL.HM | C2893: 44561 | D2893: NULL
B2894: VPL.HM | C2894: 44926 | D2894: NULL
B2895: VPL.HM | C2895: 45291 | D2895: 9254103000000
B2896: DQC.HM | C2896: 43830 | D2896: 824909982398
B2897: DQC.HM | C2897: 44196 | D2897: 940221687831
B2898: DQC.HM | C2898: 44561 | D2898: 733831365162
B2899: DQC.HM | C2899: 44926 | D2899: 989644661618
B2900: DQC.HM | C2900: 45291 | D2900: 859018218251
B2901: DQC.HM | C2901: 45657 | D2901: 813628032087
B2902: PIT.HM | C2902: 43830 | D2902: 911883953662
B2903: PIT.HM | C2903: 44196 | D2903: 551101153385
B2904: PIT.HM | C2904: 44561 | D2904: 873245853229
B2905: PIT.HM | C2905: 44926 | D2905: 791750875340
B2906: PIT.HM | C2906: 45291 | D2906: 708653549026
... B3941: CTD.HM | C3941: 44926 | D3941: 14536948503110
B3942: CTD.HM | C3942: 45107 | D3942: NULL
B3943: CTD.HM | C3943: 45473 | D3943: 21045158770378
B3944: CTD.HM | C3944: 45838 | D3944: 24884531092428
B3945: ASM.HM | C3945: 43830 | D3945: 14223773341105
B3946: ASM.HM | C3946: 44196 | D3946: 12524613811857
B3947: ASM.HM | C3947: 44561 | D3947: 11397925912454
B3948: ASM.HM | C3948: 44926 | D3948: 13749221971690
B3949: ASM.HM | C3949: 45291 | D3949: 11973153752107
B3950: ASM.HM | C3950: 45657 | D3950: 12013117890000
B3951: LHC.HN | C3951: 43830 | D3951: 757567636124
B3952: LHC.HN | C3952: 44196 | D3952: 866888005671
B3953: LHC.HN | C3953: 44561 | D3953: 1054939540593
B3954: LHC.HN | C3954: 44926 | D3954: 1416508809812
... B4137: RYG.HM | C4137: 45657 | D4137: 1692068298627
B4138: TCX.HM | D4138: Unable to collect data for the field 'TR.F.TotRevenue' and some specific identifier(s).

Sheet NTg3YTE1N2UtYzkzNy00Y2
D3: AuditId=56701_107403491_ANA_E92228B8-0296-4287-8DDD-5E0328BE46A0
D4: AuditId=70842_107403491_ANA_E92228B8-0296-4287-8DDD-5E0328BE46A0
D5: AuditId=82335_107403491_ANA_AFDAFB28-45F9-4151-951E-ABE96B778760
D6: AuditId=90527_107403491_ANA_AFDAFB28-45F9-4151-951E-ABE96B778760
D7: AuditId=98150_107403491_ANA_00985E94-2192-4CD7-B18B-C0BCBD380369
D8: AuditId=108009_107403491_ANA_00985E94-2192-4CD7-B18B-C0BCBD380369
D9: AuditId=72909_107393580_ANA_D46F9705-52F6-414B-AEC5-FB9D2C7F6DC6
D10: AuditId=87317_107393580_ANA_240465D7-8DCF-4CB9-BF22-788C97BDD91B
D11: AuditId=102459_107393580_ANA_26BE7B93-4FA1-44AD-AB3B-ABFAA9A2B8AB
D12: AuditId=110749_107393580_ANA_D66A0492-3156-444D-9561-842B5A661E74
D13: AuditId=120230_107393580_ANA_6DC35B26-5A22-4FF9-B3C0-933FF3C62F1E
D15: AuditId=74783_107345512_ANA_2F2CD24E-5C3E-4560-853D-D92B0549FC5E
... D4130: AuditId=2982_117098222_ANA_30967E00-462D-4CB7-99E6-F624516FC6B0

Sheet Sheet36
A1: =_xll.RDP.Data(Sheet1!$A$2:$A$696,"TR.InvtrDivPayoutRatio","Period=FY0 Frq=FY SDate=#1 EDate=#2 CH=Fd RH=IN;periodenddate",B2,Sheet2!$A$1,Sheet2!$A$2) -> Updated at 14:52:18
A2: =_xll.RDP.Data(Sheet1!$A$2:$A$696,"TR.F.DivPayoutRatioPct","Period=FY0 Frq=FY SDate=#1 EDate=#2 CH=Fd RH=IN;periodenddate",B2,Sheet2!$A$1,Sheet2!$A$2) -> Updated at 14:53:17 | D2: Dividend Payout Ratio - %
B3: CHP.HM | C3: 43830 | D3: 100.97014
B4: CHP.HM | C4: 44196 | D4: 49.788942
B5: CHP.HM | C5: 44561 | D5: 101.56997
B6: CHP.HM | C6: 44926 | D6: 34.547697
B7: CHP.HM | C7: 45291 | D7: 118.50852
B8: CHP.HM | C8: 45657 | D8: 79.597747
B9: V21.HN | C9: 43830 | D9: 0
B10: V21.HN | C10: 44196 | D10: 0
B11: V21.HN | C11: 44561 | D11: 0
B12: V21.HN | C12: 44926 | D12: 0
B13: V21.HN | C13: 45291 | D13: 0
B14: V21.HN | C14: 45657 | D14: NULL
B15: LIG.HN | C15: 43830 | D15: 134.1026
B16: LIG.HN | C16: 44196 | D16: 0
B17: LIG.HN | C17: 44561 | D17: 0
B18: LIG.HN | C18: 44926 | D18: 0
B19: LIG.HN | C19: 45291 | D19: NULL
B20: LIG.HN | C20: 45657 | D20: 0
B21: MCC.HN | C21: 43830 | D21: 87.268959
B22: MCC.HN | C22: 44196 | D22: 157.91891
B23: MCC.HN | C23: 44561 | D23: 103.24029
B24: MCC.HN | C24: 44926 | D24: 54.238347
B25: MCC.HN | C25: 45291 | D25: 1781.3407
B26: MCC.HN | C26: 45657 | D26: 0
B27: TET.HN | C27: 43830 | D27: 102.55643
B28: TET.HN | C28: 44196 | D28: 40.413657
B29: TET.HN | C29: 44561 | D29: 30.174714
B30: TET.HN | C30: 44926 | D30: 52.605395
B31: TET.HN | C31: 45291 | D31: 31.15469
... B33: KSD.HN | C33: 43830 | D33: 0
B34: KSD.HN | C34: 44196 | D34: NULL
B35: KSD.HN | C35: 44561 | D35: 0
B36: KSD.HN | C36: 44926 | D36: 6186.007
B37: KSD.HN | C37: 45291 | D37: 0
B38: KSD.HN | C38: 45657 | D38: NULL
B39: NBW.HN | C39: 43830 | D39: 64.260131
B40: NBW.HN | C40: 44196 | D40: 60.035945
B41: NBW.HN | C41: 44561 | D41: 65.565012
B42: NBW.HN | C42: 44926 | D42: 63.017827
B43: NBW.HN | C43: 45291 | D43: 58.10013
B44: NBW.HN | C44: 45657 | D44: 55.745526
B45: TDC.HM | C45: 43830 | D45: 111.41573
B46: TDC.HM | C46: 44196 | D46: 59.220461
B47: TDC.HM | C47: 44561 | D47: 98.602896
B48: TDC.HM | C48: 44926 | D48: 1013.4016
B49: TDC.HM | C49: 45291 | D49: NULL
B50: TDC.HM | C50: 45657 | D50: 0
B51: OGC.HM | C51: 43830 | D51: 0
B52: OGC.HM | C52: 44196 | D52: 0
B53: OGC.HM | C53: 44561 | D53: 0
B54: OGC.HM | C54: 44926 | D54: 0
B55: OGC.HM | C55: 45291 | D55: 0
B56: OGC.HM | C56: 45657 | D56: 0
B57: HTC.HN | C57: 43830 | D57: 53.120193
B58: HTC.HN | C58: 44196 | D58: 50.103313
B59: HTC.HN | C59: 44561 | D59: 73.187234
B60: HTC.HN | C60: 44926 | D60: 49.758862
B61: HTC.HN | C61: 45291 | D61: 62.378501
... B64: NVT.HM | C64: 44196 | D64: 0
B65: NVT.HM | C65: 44561 | D65: NULL
B66: NVT.HM | C66: 44926 | D66: 0
B67: NVT.HM | C67: 45291 | D67: 0
B68: NVT.HM | C68: 45657 | D68: NULL
B69: VCM.HN | C69: 43830 | D69: 151.22301
B70: VCM.HN | C70: 44196 | D70: 0
B71: VCM.HN | C71: 44561 | D71: 308.92857
B72: VCM.HN | C72: 44926 | D72: 1324.9778
B73: VCM.HN | C73: 45291 | D73: 0
B74: VCM.HN | C74: 45657 | D74: 0
B75: SPM.HM | C75: 43830 | D75: 0
B76: SPM.HM | C76: 44196 | D76: 0
B77: SPM.HM | C77: 44561 | D77: 0
B78: SPM.HM | C78: 44926 | D78: 86.438942
B79: SPM.HM | C79: 45291 | D79: 0
B80: SPM.HM | C80: 45657 | D80: 149.08389
... B87: TNT.HM | C87: 43830 | D87: 0
B88: TNT.HM | C88: 44196 | D88: NULL
B89: TNT.HM | C89: 44561 | D89: 0
B90: TNT.HM | C90: 44926 | D90: 0
B91: TNT.HM | C91: 45291 | D91: 0
B92: TNT.HM | C92: 45657 | D92: 0
B93: HU1.HM | C93: 43830 | D93: 81.850133
B94: HU1.HM | C94: 44196 | D94: 119.80002
B95: HU1.HM | C95: 44561 | D95: 0
B96: HU1.HM | C96: 44926 | D96: 0
B97: HU1.HM | C97: 45291 | D97: NULL
B98: HU1.HM | C98: 45657 | D98: 0
B99: SBA.HM | C99: 43830 | D99: 78.064692
B100: SBA.HM | C100: 44196 | D100: 75.233146
B101: SBA.HM | C101: 44561 | D101: 51.455853
B102: SBA.HM | C102: 44926 | D102: 64.29698
B103: SBA.HM | C103: 45291 | D103: 65.364047
B104: SBA.HM | C104: 45657 | D104: 117.20619
B105: IDV.HN | C105: 44104 | D105: 25.665771
B106: IDV.HN | C106: 44469 | D106: 12.317353
B107: IDV.HN | C107: 44834 | D107: 7.4763391
B108: IDV.HN | C108: 45199 | D108: 8.8508529
B109: IDV.HN | C109: 45565 | D109: 37.66837
...

Sheet Sheet35
A1: =_xll.RDP.Data(Sheet1!$A$2:$A$696,"TR.TOTALNUMBEROFSHARESOUTSTANDING","Period=FY0 Frq=FY SDate=#1 EDate=#2 CH=Fd RH=IN;periodenddate",B2,Sheet2!$A$1,Sheet2!$A$2) -> Updated at 14:51:21
D2: Total Number of Shares Outstanding
B3: CHP.HM | D3: NULL
B4: V21.HN | D4: NULL
B5: LIG.HN | D5: NULL
B6: MCC.HN | D6: NULL
B7: TET.HN | D7: NULL
B8: KSD.HN | D8: NULL
B9: NBW.HN | D9: NULL
B10: TDC.HM | D10: NULL
B11: OGC.HM | D11: NULL
B12: HTC.HN | D12: NULL
B13: NVT.HM | D13: NULL
B14: VCM.HN | D14: NULL
... B697: TCX.HM | D697: NULL

Sheet Sheet38
A1: =_xll.RDP.Data(Sheet1!$A$2:$A$696,"TR.InvtrDivPayoutRatio","Period=FY0 Frq=FY SDate=#1 EDate=#2 CH=Fd RH=IN;periodenddate",B2,Sheet2!$A$1,Sheet2!$A$2) -> Updated at 14:55:37
A2: =_xll.RDP.Data(Sheet1!$A$2:$A$696,"TR.InvtrEPS5YearProjGr","Period=FY0 Frq=FY SDate=#1 EDate=#2 CH=Fd RH=IN;periodenddate",B2,Sheet2!$A$1,Sheet2!$A$2) -> Updated at 14:57:27 | B2: Output parameter 'PERIODENDDATE' is unrecognized. This could possibly happen because of mismatch between top level function expression and its usage in output. Make sure that you used exactly 1:1 identical expressions.
